Workbook
Name destinos: 'EGR 1-copiar en word 0 EGR'!#REF!
Name destinos: 'EGR2 2--copiar en word 1 EGR'!#REF!
Name no: 'EGR 1-copiar en word 0 EGR'!#REF!
Name no: 'EGR2 2--copiar en word 1 EGR'!#REF!
Name tratamientos: 'EGR 1-copiar en word 0 EGR'!#REF!
Name tratamientos: 'EGR2 2--copiar en word 1 EGR'!#REF!

Sheet INDICACIONES
A1: 1 | B1: Rellenar mediciones aéreas
A2: 2 | B2: Rellenar mediciones subterráneas
A3: 3 | B3: ajustar mediciones por TTMM
A4: 4 | B4: chequear la suma tota por TTMM
A6: 6 | B6: ajustar columna derecha de items y eliminar filas con valores cero
A7: 7 | B7: ¿seguro que está todo OK?
A8: 8 | B8: hacer una copia de seguridad
A9: 9 | B9: entonces a preparar pot TTMM:
B10: Se copia la hoja tantas veces como ttmm hay
B11: Se borran las columnas de mediciones

Sheet 1.- datos aéreo
A1: APOYOS
B2: DATOS POR TIPO DE APOYO
A3: TIPO DE APOYO | B3: Peso | E3: Excavación | H3: Hormigonado | I3: BASTON AISLADOR | J3: CADENA SUS | K3: CADENA AM
A4: FL-PAS | B4: 93 | E4: 32.5 | H4: 37.4 | I4: 3 | J4: 0 | K4: 3
A5: FL | B5: 90 | E5: 32 | H5: 36.16 | I5: 3 | J5: 0 | K5: 3
A6: SUS-AL | B6: 40 | E6: 28 | H6: 31.64 | I6: 3 | J6: 3 | K6: 0
A7: ANC-ANG | B7: 70 | E7: 31 | H7: =+E7*H5/E5 -> 35.03 | I7: 6 | J7: 0 | K7: 6
B9: PROCESO
A10: 1 | B10: Se traen los datos de apoyos de la carpeta de tablas
A11: 2 | B11: se añade la parte verde
A12: 3 | B12: se obtienen los totales por TTMM | U12: tmm 1 | V12: ttmm2 | W12: ttmm3
A13: paso 1.- DISPONIBLE EN LA CARPETA DE #TABLAS DE CADA AP | R13: paso 2.- SE ASIGNA A CADA APOYO CON LA TABLA DE ARRIBA Y SE OBTIENENLSO TOTALES | U13: paso 3.- REPARTO POR TTMM | X13: herrajes 30 kV por apoyo DX LA280 | AA13: herrajes 220 kV por apoyo DX LA280 | AD13: herrajes 220 kV por apoyo TX LA510
A14: PUNTO/NUMERO APOYO | B14: TRAMO DE LÍNEA | E14: TIPO APOYO | H14: Tensión Línea | I14: ALTURA CRUCETA INFERIOR (m) | J14: ALTURA TOTAL DEL APOYO (m) | K14: OCUPACIÓN PERMANENTE (m2) | L14: OCUPACIÓN TEMPORAL (m2) | M14: X U.T.M. ETRS89 HUSO 30 | N14: Y U.T.M. ETRS89 HUSO 30 | O14: Término municipal | P14: Provincia | Q14: Comunidad autónoma | R14: PESO (Tn) | S14: Exv (m3) | T14: Hor (m3) | U14: PESO (Tn) | V14: Exv (m3) | W14: Hor (m3) | X14: CADENAS DE SUSPENSION | Y14: CADENAS DE AMARRE | Z14: BASTONES | AA14: CADENAS DE SUSPENSION | AB14: CADENAS DE AMARRE | AC14: BASTONES | AD14: CADENAS DE SUSPENSION | AE14: CADENAS DE AMARRE | AF14: BASTONES
Q16: TOTALES | R16: =SUM(R15:R15) -> 0 | S16: =SUM(S15:S15) -> 0 | T16: =SUM(T15:T15) -> 0 | U16: =SUM(U15:U15) -> 0 | V16: =SUM(V15:V15) -> 0 | W16: =SUM(W15:W15) -> 0 | X16: =SUM(X15:X15) -> 0 | Y16: =SUM(Y15:Y15) -> 0 | ... AF16: =SUM(AF15:AF15) -> 0
R18: TEST | X18: CADENAS DE SUSPENSION | Y18: CADENAS DE AMARRE | Z18: BASTONES | AA18: CADENAS DE SUSPENSION | AB18: CADENAS DE AMARRE | AC18: BASTONES | AD18: CADENAS DE SUSPENSION | AE18: CADENAS DE AMARRE | AF18: BASTONES
R19: =+R16/U16 -> #DIV/0! | S19: =+S16/V16 -> #DIV/0! | T19: =+T16/W16 -> #DIV/0! | X19: herrajes 30 kV por apoyo DX LA280 | AA19: herrajes 220 kV por apoyo DX LA280 | AD19: herrajes 220 kV por apoyo TX LA510
A20: CABLE AÉREO Y HERRAJES
B21: PROCESO
A22: 1 | B22: Se traen los datos LONGITUDES DE TRAMO Y TTMM de la carpeta de tablas | K22: la280 | L22: 0.973
A23: 2 | B23: se añade la parte verde | K23: opgw | L23: 0.68
A24: 3 | B24: se obtienen los totales por TTMM | K24: la510 | L24: 1.6
A26: TRAMO | B26: ORIGEN | C26: X UTM ETRS89 HUSO31 | D26: Y UTM ETRS89 HUSO31 | E26: FINAL | F26: X UTM ETRS89 HUSO31 | G26: Y UTM ETRS89 HUSO31 | H26: TIPO | I26: Nº CIRC | J26: LONGITUD DEL TRAMO (m) | L26: ORIGEN | M26: DESCRIPCION | N26: ORIGEN X ETRS89 HUSO 30 | O26: ORIGEN Y ETRS89 HUSO 30 | P26: TTMM | Q26: PROVINCIA | R26: COMUNIDAD
A27: 1 | B27: PO/SE XXX | C27: 472975.95 | D27: 4388875.8 | E27: PF/SE SONREUS | F27: 472666.03 | G27: 4388926 | H27: SUBTERRÁNEO | I27: 1 | J27: 427 | L27: PO/SE XXX | N27: =C27 -> 472975.95 | O27: =D27 -> 4388875.8 | P27: PALMA | Q27: MALLORCA | R27: ISLAS BALEARES
A28: LONGITUDES TOTALES (m) | J28: =J27 -> 427 | L28: PF/SE SONREUS | N28: 472666.03 | O28: 4388926 | P28: PALMA | Q28: MALLORCA | R28: ISLAS BALEARES
A36: % terminales | B36: 0.08
A37: TRAMO | B37: ORIGEN | C37: X UTM ETRS89 HUSO31 | D37: Y UTM ETRS89 HUSO31 | E37: FINAL | F37: X UTM ETRS89 HUSO31 | G37: Y UTM ETRS89 HUSO31 | H37: TIPO | I37: Nº CIRC | J37: LONGITUD DEL TRAMO (m) | K37: LONGITUD EN EL TTMM DE ARRATZUA - UBARRUNDIA (Álava) | L37: LONGITUD EN EL TTMM DE ZIGOITIA (Álava)
A38: 1 | B38: PO-1 | C38: 474495.75 | D38: 4388125.9 | E38: BIF-1 | H38: SUBTERRÁNEO | I38: 1 | J38: 3.31 | N38: L1 | O38: =J38+J40 -> 2192.64
A39: 2 | B39: PO-2 | C39: 474491.42 | D39: 4388135 | E39: BIF-1 | H39: SUBTERRÁNEO | I39: 2 | J39: 13.36 | N39: L2 | O39: =J39+J40 -> 2202.69
A40: 3 | B40: BIF-1 | E40: PF/ SE XXX | F40: 472979.58 | G40: 4388842.7 | H40: SUBTERRÁNEO | I40: 4 | J40: 2189.33 | K40: 0 | N40: LT | O40: =SUM(O38:O39) -> 4395.33
A41: LONGITUD TOTAL EJE TRAMO SUBTERRÁNEO 30 kV (m) | J41: =SUM(J38:J40) -> 2206 | K41: 0 | L41: =#REF! -> #REF! | O41: =O40/2 -> 2197.665
A42: LONGITUDES TOTALES (m) | J42: =J41 -> 2206 | K42: =+K41 -> 0 | L42: =+L41 -> #REF!
Q46: LONG | R46: =+#REF! -> #REF! | S46: =+#REF! -> #REF! | T46: =+#REF! -> #REF! | U46: =+#REF! -> #REF! | V46: =+#REF! -> #REF! | W46: =+#REF! -> #REF! | X46: =+#REF! -> #REF! | Y46: =+#REF! -> #REF! | ... AA46: =+#REF! -> #REF! | AB46: =SUM(R46:AA46) -> #REF!
Q47: % | R47: =+R46/$AB$46 -> #REF! | S47: =+S46/$AB$46 -> #REF! | T47: =+T46/$AB$46 -> #REF! | U47: =+U46/$AB$46 -> #REF! | V47: =+V46/$AB$46 -> #REF! | W47: =+W46/$AB$46 -> #REF! | X47: =+X46/$AB$46 -> #REF! | Y47: =+Y46/$AB$46 -> #REF! | ... AA47: =+AA46/$AB$46 -> #REF! | AB47: =SUM(R47:AA47) -> #REF!
B48: 1 hay, 0 no hay | E48: esta columna no puede estar vacia | H48: =+K37 -> LONGITUD EN EL TTMM DE ARRATZUA - UBARRUNDIA (Álava) | I48: =+L37 -> LONGITUD EN EL TTMM DE ZIGOITIA (Álava) | J48: =+M37 -> 0 | K48: nº subcondcutores | L48: nº circuitos | M48: total cables del circuito | N48: peso cable (kg/m) | O48: MEDICION
A49: nº apoyos | AB49: =+O49-SUM(R49:AA49) -> 0
A50: Conductor tipo LA280 cctos 30 kV | P50: =+'PRESUPUESTO P'!C64 -> kg | AB50: =+O50-SUM(R50:AA50) -> 0
A51: Conductor tipo LA280 cctos 220 kV | P51: =+'PRESUPUESTO P'!C65 -> kg | AB51: =+O51-SUM(R51:AA51) -> 0
A52: Conductor tipo LA510 cctos 220 kV | P52: =+'PRESUPUESTO P'!C66 -> kg | AB52: =+O52-SUM(R52:AA52) -> 0
A53: Cable compuesto OPGW cctos 30 kV | P53: =+'PRESUPUESTO P'!C67 -> m | AB53: =+O53-SUM(R53:AA53) -> 0
A54: Cable compuesto OPGW cctos 220 kV | P54: =+'PRESUPUESTO P'!C68 -> m | AB54: =+O54-SUM(R54:AA54) -> 0
A55: Aislador Composite ccto 30 kV DX LA280 | P55: =+'PRESUPUESTO P'!C69 -> ud | AB55: =+O55-SUM(R55:AA55) -> 0
A56: Aislador Composite ccto 30 kV DX LA280 en apoyos compartidos 220 kV-ap06-08-14 | P56: =+'PRESUPUESTO P'!C70 -> ud | Q56: SOLO AP06-08-14 | AB56: =+O56-SUM(R56:AA56) -> 0
A57: Aislador Composite ccto 220 kV DX LA280 | P57: =+'PRESUPUESTO P'!C71 -> ud | AB57: =+O57-SUM(R57:AA57) -> 0
A58: Aislador Composite ccto 220 kV TX LA510 | P58: =+'PRESUPUESTO P'!C72 -> ud | AB58: =+O58-SUM(R58:AA58) -> 0
A59: Cadena suspensión ccto 30 kV DX LA280 | P59: =+'PRESUPUESTO P'!C73 -> ud | AB59: =+O59-SUM(R59:AA59) -> 0
A60: Cadena suspensión ccto 30 kV DX LA280 en apoyos compartidos 220 kV-ap06-08-14 | P60: =+'PRESUPUESTO P'!C74 -> ud | Q60: SOLO AP06-08-14 | AB60: =+O60-SUM(R60:AA60) -> 0
A61: Cadena suspensióne ccto 220 kV DX LA280 | P61: =+'PRESUPUESTO P'!C75 -> ud | AB61: =+O61-SUM(R61:AA61) -> 0
A62: Cadena suspensión ccto 220 kV TX LA510 | P62: =+'PRESUPUESTO P'!C76 -> ud | AB62: =+O62-SUM(R62:AA62) -> 0
A63: Cadena amarre ccto 30 kV DX LA280 | P63: =+'PRESUPUESTO P'!C77 -> ud | AB63: =+O63-SUM(R63:AA63) -> 0
A64: Cadena amarre ccto 30 kV DX LA280 en apoyos compartidos 220 kV-ap06-08-14 | P64: =+'PRESUPUESTO P'!C78 -> ud | Q64: SOLO AP06-08-14 | AB64: =+O64-SUM(R64:AA64) -> 0
A65: Cadena amarre ccto 220 kV DX LA280 | P65: =+'PRESUPUESTO P'!C79 -> ud | AB65: =+O65-SUM(R65:AA65) -> 0
A66: Cadena amarre ccto 220 kV TX LA510 | P66: =+'PRESUPUESTO P'!C80 -> ud | AB66: =+O66-SUM(R66:AA66) -> 0
A67: Cadena suspensión OPGW ccto 30 kV DX LA280 | P67: =+'PRESUPUESTO P'!C81 -> ud | AB67: =+O67-SUM(R67:AA67) -> 0
A68: Cadena suspensión OPGW ccto 220 kV DX LA280 | P68: =+'PRESUPUESTO P'!C82 -> ud | AB68: =+O68-SUM(R68:AA68) -> 0
A69: Cadena suspensión OPGW ccto 220 kV TX LA510 | P69: =+'PRESUPUESTO P'!C83 -> ud | AB69: =+O69-SUM(R69:AA69) -> 0
A70: Cadena amarre OPGW ccto 30 kV DX LA280 | P70: =+'PRESUPUESTO P'!C84 -> ud | AB70: =+O70-SUM(R70:AA70) -> 0
A71: Cadena amarre OPGW ccto 220 kV DX LA280 | P71: =+'PRESUPUESTO P'!C85 -> ud | AB71: =+O71-SUM(R71:AA71) -> 0
A72: Cadena amarre OPGW ccto 220 kV TX LA510 | P72: =+'PRESUPUESTO P'!C86 -> ud | AB72: =+O72-SUM(R72:AA72) -> 0
A73: Placa Riesgo Eléctrico y señalización | P73: =+'PRESUPUESTO P'!C87 -> ud | AB73: =+O73-SUM(R73:AA73) -> 0
A74: Amortuiguador separador conductor tipo LA280 cctos 30 kV | P74: =+'PRESUPUESTO P'!C88 -> ud | Q74: ajustar enteros para que cuadre | AB74: =+O74-SUM(R74:AA74) -> 0
A75: Amortuiguador separador conducto tipo LA280 cctos 220 kV | P75: =+'PRESUPUESTO P'!C89 -> ud | Q75: ajustar enteros para que cuadre | AB75: =+O75-SUM(R75:AA75) -> 0
A76: Amortuiguador separador conductor tipo LA510 cctos 220 kV | P76: =+'PRESUPUESTO P'!C90 -> ud | Q76: ajustar enteros para que cuadre | AB76: =+O76-SUM(R76:AA76) -> 0
A77: Amortuiguador OPGW ccto 30 kV | P77: =+'PRESUPUESTO P'!C91 -> ud | Q77: ajustar enteros para que cuadre | AB77: =+O77-SUM(R77:AA77) -> 0 | AC77: se quita uno para cuadrar ddecimales
A78: Amortuiguador OPGW ccto 220 kV | P78: =+'PRESUPUESTO P'!C92 -> ud | Q78: ajustar enteros para que cuadre | AB78: =+O78-SUM(R78:AA78) -> 0
A79: Salvapajaros OPGW ccto 30 kV | P79: =+'PRESUPUESTO P'!C93 -> ud | Q79: ajustar enteros para que cuadre | AB79: =+O79-SUM(R79:AA79) -> 0
A80: Salvapajaros OPGW ccto 220 kV | P80: =+'PRESUPUESTO P'!C94 -> ud | Q80: ajustar enteros para que cuadre | AB80: =+O80-SUM(R80:AA80) -> 0
A81: PAT apoyo | P81: =+'PRESUPUESTO P'!C95 -> ud | AB81: =+O81-SUM(R81:AA81) -> 0
A82: Conexión FO-1 PA SI HAY TRAMO AÉREO | P82: =+'PRESUPUESTO P'!C96 -> ud | AB82: =+O82-SUM(R82:AA82) -> 0

Sheet 2.- datos subt
A1: LINEA 30 KV SUBTERRANEA-1 CCTO | C1: TTMM 1 | D1: TTMM 2 | E1: TTMM 3
A2: nº de cables aislados 30 kV/240mm2 | B2: 6 | E2: rellenar a mano las cedas verdes sin crear referencias circulares
A3: nº de cables aislados 30 kV/630 mm2 | B3: 6 | E3: rellenar a mano las cedas verdes sin crear referencias circulares
A4: nº de cables FO | B4: 2 | C4: =+'1.- datos aéreo'!K37 -> LONGITUD EN EL TTMM DE ARRATZUA - UBARRUNDIA (Álava) | D4: =+'1.- datos aéreo'!L37 -> LONGITUD EN EL TTMM DE ZIGOITIA (Álava) | F4: test
A5: Cajas empalmes FO 30 kV | B5: =SUM(C5:E5) -> 0 | F5: =+B5-SUM(C5:E5) -> 0
A6: longitud zanja 30 kV | B6: =+'1.- datos aéreo'!J41 -> 2206 | C6: =+'1.- datos aéreo'!K41 -> 0 | F6: =+B6-SUM(C6:E6) -> 2206
A7: longitud perforación 30 kV | B7: =+B8*110/2 -> 0 | C7: =+C8*110/2 -> 0 | D7: =+D8*110/2 -> 0 | F7: =+B7-SUM(C7:E7) -> 0 | H7: 4 PHD
A8: nº de pozos | B8: 0 | C8: 0 | D8: 0 | F8: =+B8-SUM(C8:E8) -> 0 | H8: 2 pozos por cada perforacion | J8: revisad el listado de cruces en tramos subt
A9: longiud cable 30 kV entre terminales 240 mm2 | B9: =+B7*1.1+(B6-B7)*1.05 -> 2316.3 | C9: =+C7*1.1+(C6-C7)*1.05 -> 0 | D9: =+D7*1.1+(D6-D7)*1.05 -> 0 | F9: =+B9-SUM(C9:E9) -> 2316.3
A10: longiud cable 30 kV entre terminales 630 mm2 | B10: =+B7*1.1+(B6-B7)*1.05 -> 2316.3 | C10: =+C8*1.1+(C7-C8)*1.05 -> 0 | D10: =+D8*1.1+(D7-D8)*1.05 -> 0 | F10: =+B10-SUM(C10:E10) -> 2316.3
A11: longiud cable 30 kV total 240 mm2 | B11: ='1.- datos aéreo'!J38*3+'1.- datos aéreo'!J39*3+'1.- datos aéreo'!J40*6 -> 13185.99 | C11: =+C9*$B$3 -> 0 | D11: =+D9*$B$3 -> 0 | F11: =+B11-SUM(C11:E11) -> 13185.99
A12: longiud cable 30 kV total 630 mm2 | B12: ='1.- datos aéreo'!J38*3+'1.- datos aéreo'!J39*3+'1.- datos aéreo'!J40*6 -> 13185.99 | C12: =+C11*$B$3 -> 0 | D12: =+D11*$B$3 -> 0 | F12: =+B12-SUM(C12:E12) -> 13185.99
A13: longiud cable FO CCTO 30 kV total | B13: =B9*B4 -> 4632.6 | C13: =+C11/$B$3*$B$4 -> 0 | D13: =+D11/$B$3*$B$4 -> 0 | F13: =+B13-SUM(C13:E13) -> 4632.6
A14: CE empalmes 30 kV | B14: 0 | C14: =+INT(C9/700)-1 -> -1 | F14: =+B14-SUM(C14:E14) -> 1
A15: Nº empalmes 30 kV | B15: =+B14*$B$3 -> 0 | C15: =+C14*$B$3 -> -6 | D15: =+D14*$B$3 -> 0 | F15: =+B15-SUM(C15:E15) -> 6
A16: nº tramos subterraneos 30 Kv independientes | B16: 1 | C16: 1 | D16: 0 | F16: =+B16-SUM(C16:E16) -> 0
A17: terminales 30 kV/240mm2 | B17: =B2 -> 6 | C17: =+C15*9 -> -54 | D17: =+D15*9 -> 0 | F17: =+B17-SUM(C17:E17) -> 60
A18: terminales 30 kV/630mm2 | B18: =B3 -> 6 | C18: =+C16*9 -> 9 | D18: =+D16*9 -> 0 | F18: =+B18-SUM(C18:E18) -> -3
A19: cajas puesta a tierra 30 kV | B19: 0 | C19: 0 | D19: 0 | F19: =+B19-SUM(C19:E19) -> 0
B20: E/KM | C20: =+C6/(C14+1) -> #DIV/0! | D20: =+D6/(D14+1) -> 0
A21: LINEA 220 KV SUBTERRANEA-1 CCTO
A22: nº de cables aislados 220 kV | B22: 3
A23: nº de cables FO ctto 220 kV | B23: 3
A24: Cajas empalmes FO 220 kV | B24: 0
A25: longitud zanja 220 kV | B25: 430.47
A26: longitud perforación 220 kV | B26: 0
A27: nº de pozos | B27: 0 | H27: 2 pozos por cada perforacion | J27: =+J8 -> revisad el listado de cruces en tramos subt
A28: longiud cable 220 kV entre terminales | B28: =B25*1.05 -> 451.9935
A29: longiud cable 220 kV total | B29: =B28*B22+10+10 -> 1375.9805
A30: longiud cable FO CCTO 220 kV total | B30: =B28*B23+200 -> 1555.9805
A31: CE empalmes 220 kV | B31: 0
A32: Nº empalmes 220 kV | B32: 0
A33: nº tramos subterraneos 220 kV indep | B33: 1
A34: terminales 220 kV | B34: 6
A35: cajas puesta a tierra 220 kV | B35: 3 | C35: 3 y 3
A36: apoyos PAS
A37: autoválvulas 220 kV

Sheet Cruces
A1: Núm. | B1: Denominación | C1: Organismo | D1: X U.T.M. ETRS89 HUSO 30 | E1: Y U.T.M. ETRS89 HUSO 30 | F1: Término municipal | G1: Provincia | K1: Paralelismo Nº | L1: Denominación | M1: Organismo | N1: PUNTO INICIAL-FINAL | O1: X U,T,M, ETRS89 HUSO 30 | P1: Y U,T,M, ETRS89 HUSO 30 | Q1: Término municipal | R1: Provincia
A2: CR-01 | B2: Tubería distribución agua | D2: 474305.25 | E2: 4388413.4 | F2: Marratxi | G2: Mallorca | K2: PA-01 | L2: Tubería distribución agua | N2: PA-01 PI | O2: 474433.61 | P2: 4388142.7 | Q2: Marratxi | R2: Mallorca
A3: CR-02 | B3: Carretera Ma-2031 | D3: 474148.21 | E3: 4388651.2 | F3: Marratxi | G3: Mallorca | N3: CR-01 | O3: 474305.25 | P3: 4388413.4 | Q3: Marratxi | R3: Mallorca
A4: CR-03 | B4: Cauce | D4: 473383.91 | E4: 4388960 | F4: Palma | G4: Mallorca | K4: PA-02 | L4: Gasoducto ramal 1 Gasoducto ramal 2 | M4: Redexis Gas Transporte, S.L. | N4: PA-01 PI | O4: 474433.61 | P4: 4388142.7 | Q4: Marratxi | R4: Mallorca
A5: CR-04 | B5: Cauce | D5: 473355.32 | E5: 4388988.5 | F5: Palma | G5: Mallorca | N5: PA-02 PF | O5: 473253.86 | P5: 4389071.5 | Q5: Palma | R5: Mallorca
A6: CR-05 | B6: Línea eléctrica aérea | C6: REDEIA | D6: 473320.58 | E6: 4389023.2 | F6: Palma | G6: Mallorca | K6: PA-03 | L6: Gasoducto ramal 2 Gasoducto ramal 3 | M6: Redexis Gas Transporte, S.L. | N6: PA-02 PF | O6: 473253.86 | P6: 4389071.5 | Q6: Palma | R6: Mallorca
A7: CR-06 | B7: Línea eléctrica aérea | D7: 473200.95 | E7: 4389018.9 | F7: Palma | G7: Mallorca | Q7: Palma | R7: Mallorca
A11: CR-07 | B11: Gasoducto | C11: Redexis Gas Transporte, S.L. | D11: 472878.58 | E11: 4388794.7 | F11: Palma | G11: Mallorca | K11: PA-04 | L11: Gasoducto ramal 2 Gasoducto ramal 3 | M11: Redexis Gas Transporte, S.L. | Q11: Palma | R11: Mallorca
A12: CR-08 | B12: Camí Son Reus | D12: 472846.71 | E12: 4388794.9 | F12: Palma | G12: Mallorca | N12: PA-04 PF | O12: 472863.01 | P12: 4388784.1 | Q12: Palma | R12: Mallorca
A13: CR-09 | B13: Gasoducto | C13: Redexis Gas Transporte, S.L. | D13: 472834.85 | E13: 4388807 | F13: Palma | G13: Mallorca
A14: CR-10 | B14: Línea eléctrica | D14: 472734.25 | E14: 4388909.3 | F14: Palma | G14: Mallorca

Sheet PRESUPUESTO P
H1: =+'1.- datos aéreo'!K37 -> LONGITUD EN EL TTMM DE ARRATZUA - UBARRUNDIA (Álava) | I1: =+'1.- datos aéreo'!L37 -> LONGITUD EN EL TTMM DE ZIGOITIA (Álava) | J1: =+'1.- datos aéreo'!M37 -> 0
A2: CAPÍTULO 1. LÍNEA SUBTERRÁNEA | H2: TTMM 1 | I2: TTMM 2 | J2: TTMM 3
A3: CAPÍTULO 1.1 MATERIALES LÍNEA SUBTERRÁNEA | H3: =+'1.- datos aéreo'!K42 -> 0 | I3: =+'1.- datos aéreo'!L42 -> #REF! | J3: =+'1.- datos aéreo'!M42 -> 0 | K3: =SUM(H3:J3) -> #REF! | L3: LONG EJE
A4: Partida | B4: Concepto | C4: Ud. | D4: Cantidad | E4: Precio Ud | F4: Importe (€) | H4: =+H3/$K$3 -> #REF! | I4: =+I3/$K$3 -> #REF! | J4: =+J3/$K$3 -> #REF! | K4: =SUM(H4:J4) -> #REF! | L4: % LONG EJE
A5: 1.1.1 | B5: Cable aislado 30 kV/240 mm2 | C5: m | D5: =+'2.- datos subt'!B11 -> 13185.99 | E5: 4 | F5: =D5*E5 -> 52743.96 | G5: =+D5-SUM(H5:J5) -> 13185.99 | H5: =+'2.- datos subt'!C11 -> 0 | I5: =+'2.- datos subt'!D11 -> 0 | J5: =+'2.- datos subt'!E11 -> 0
A6: 1.1.1 | B6: Cable aislado 30 kV/630 mm2 | C6: m | D6: =+'2.- datos subt'!B12 -> 13185.99 | E6: 6.5 | F6: =D6*E6 -> 85708.935 | G6: =+D6-SUM(H6:J6) -> 13185.99 | H6: =+'2.- datos subt'!C13 -> 0 | I6: =+'2.- datos subt'!D13 -> 0 | J6: =+'2.- datos subt'!E13 -> 0
A7: 1.1.2 | B7: Cable aislado 220 kV | C7: m | D7: =+'2.- datos subt'!B28 -> 451.9935 | E7: 120 | F7: =D7*E7 -> 54239.22 | G7: =+D7-SUM(H7:J7) -> 451.9935 | H7: 0 | I7: 0 | J7: 0
A8: 1.1.3 | B8: Terminales 30 kV 240 mm2 | C8: ud | D8: =+'2.- datos subt'!B17 -> 6 | E8: =ROUNDUP(160*240/630,0) -> 61 | F8: =D8*E8 -> 366 | G8: =+D8-SUM(H8:J8) -> 5 | H8: =+'2.- datos subt'!C16 -> 1 | I8: =+'2.- datos subt'!D16 -> 0 | J8: =+'2.- datos subt'!E16 -> 0 | K8: =2.3*1.05*6 -> 14.49
A9: 1.1.3 | B9: Terminales 30 kV 630 mm2 | C9: ud | D9: =+'2.- datos subt'!B18 -> 6 | E9: 160 | F9: =D9*E9 -> 960 | G9: =+D9-SUM(H9:J9) -> -3 | H9: =+'2.- datos subt'!C18 -> 9 | I9: =+'2.- datos subt'!D18 -> 0 | J9: =+'2.- datos subt'!E18 -> 0
A10: 1.1.4 | B10: Terminales 220 kV | C10: ud | D10: =+'2.- datos subt'!B34 -> 6 | E10: 7000 | F10: =D10*E10 -> 42000 | G10: =+D10-SUM(H10:J10) -> 6 | H10: 0 | I10: 0 | J10: 0
A11: 1.1.5 | B11: Autoválvulas 220 kV | C11: ud | D11: =+'2.- datos subt'!B37 -> 0 | E11: 3300 | F11: =D11*E11 -> 0 | G11: =+D11-SUM(H11:J11) -> 0 | H11: 0 | I11: 0 | J11: 0
A12: 1.1.6 | B12: Cámaras de empalmes 30 kV | C12: ud | D12: =+'2.- datos subt'!B14 -> 0 | E12: 300 | F12: =D12*E12 -> 0 | G12: =+D12-SUM(H12:J12) -> 1 | H12: =+'2.- datos subt'!C14 -> -1 | I12: =+'2.- datos subt'!D14 -> 0 | J12: =+'2.- datos subt'!E14 -> 0
A13: 1.1.7 | B13: Cámaras de empalmes 220 kV | C13: ud | D13: =+'2.- datos subt'!B31 -> 0 | E13: 950 | F13: =D13*E13 -> 0 | G13: =+D13-SUM(H13:J13) -> 0 | H13: 0 | I13: 0 | J13: 0
A14: 1.1.8 | B14: Empalmes 30 kV | C14: ud | D14: =+'2.- datos subt'!B15 -> 0 | E14: 180 | F14: =D14*E14 -> 0 | G14: =+D14-SUM(H14:J14) -> 6 | H14: =+'2.- datos subt'!C15 -> -6 | I14: =+'2.- datos subt'!D15 -> 0 | J14: =+'2.- datos subt'!E15 -> 0
A15: 1.1.9 | B15: Empalmes 220 kV | C15: ud | D15: =+'2.- datos subt'!B32 -> 0 | E15: 5000 | F15: =D15*E15 -> 0 | G15: =+D15-SUM(H15:J15) -> 0 | H15: 0 | I15: 0 | J15: 0
A16: 1.1.10 | B16: Caja de puesta a tierra 30 kV | C16: ud | D16: =+'2.- datos subt'!B19 -> 0 | E16: 640 | F16: =D16*E16 -> 0 | G16: =+D16-SUM(H16:J16) -> 0 | H16: =+'2.- datos subt'!C19 -> 0 | I16: =+'2.- datos subt'!D19 -> 0 | J16: =+'2.- datos subt'!E19 -> 0
A17: 1.1.11 | B17: Caja de puesta a tierra 220 kV intemperie | C17: ud | D17: =+D18 -> 3 | E17: 3100 | F17: =D17*E17 -> 9300 | G17: =+D17-SUM(H17:J17) -> 3 | H17: 0 | I17: 0 | J17: 0
A18: 1.1.11 | B18: Caja de puesta a tierra 220 kV intemperie con descargador | C18: ud | D18: =+'2.- datos subt'!B35 -> 3 | E18: 3200 | F18: =D18*E18 -> 9600 | G18: =+D18-SUM(H18:J18) -> 3 | H18: 0 | I18: 0 | J18: 0
A19: 1.1.12 | B19: Pequeño material p.a.t pantallas | C19: ud | D19: 2 | E19: 1000 | F19: =D19*E19 -> 2000 | G19: =+D19-SUM(H19:J19) -> 0 | H19: 2 | I19: 0 | J19: 0
A20: 1.1.13 | B20: Cable comunicaciones FO ccto 30 kV | C20: m | D20: =+'2.- datos subt'!B9*'2.- datos subt'!B4 -> 4632.6 | E20: 1 | F20: =D20*E20 -> 4632.6 | G20: =+D20-SUM(H20:J20) -> 4632.6 | H20: =+'2.- datos subt'!C13 -> 0 | I20: =+'2.- datos subt'!D13 -> 0 | J20: =+'2.- datos subt'!E13 -> 0
A21: 1.1.14 | B21: Cable comunicaciones FO ccto 220 kV | C21: m | D21: =+'2.- datos subt'!B28*'2.- datos subt'!B23 -> 1355.9805 | E21: 1.2 | F21: =D21*E21 -> 1627.1766 | G21: =+D21-SUM(H21:J21) -> 1355.9805 | H21: 0 | I21: 0 | J21: 0
A22: 1.1.15 | B22: Cajas empalme FO ccto 30 kV | C22: ud | D22: =+'2.- datos subt'!B5 -> 0 | E22: 300 | F22: =D22*E22 -> 0 | G22: =+D22-SUM(H22:J22) -> 0 | H22: =+'2.- datos subt'!C5 -> 0 | I22: =+'2.- datos subt'!D5 -> 0 | J22: =+'2.- datos subt'!E5 -> 0
A23: 1.1.16 | B23: Cajas empalme FO ccto 220 kV | C23: ud | D23: =+'2.- datos subt'!B24 -> 0 | E23: 300 | F23: =D23*E23 -> 0 | G23: =+D23-SUM(H23:J23) -> 0 | H23: 0 | I23: 0 | J23: 0
A24: TOTAL CAPÍTULO 1.1.- | F24: =SUM(F5:F23) -> 263177.89
A26: CAPÍTULO 1.2. MONTAJE LÍNEA SUBTERRÁNEA
A27: Partida | B27: Concepto | C27: Ud. | D27: Cantidad | E27: Precio Ud | F27: Importe (€)
A28: 1.2.1 | B28: =+B5 -> Cable aislado 30 kV/240 mm2 | C28: =+C5 -> m | D28: =+D5 -> 13185.99 | E28: 1.1 | F28: =D28*E28 -> 14504.589 | G28: =+D28-SUM(H28:J28) -> 13185.99 | H28: =+H5 -> 0 | I28: =+I5 -> 0 | J28: =+J5 -> 0
A29: 1.2.2 | B29: =+B6 -> Cable aislado 30 kV/630 mm2 | C29: =+C6 -> m | D29: =+D6 -> 13185.99 | E29: 1.5 | F29: =D29*E29 -> 19778.985 | G29: =+D29-SUM(H29:J29) -> 13185.99 | H29: =+H6 -> 0 | I29: =+I6 -> 0 | J29: =+J6 -> 0
A30: 1.2.2 | B30: =+B7 -> Cable aislado 220 kV | C30: =+C7 -> m | D30: =+D7 -> 451.9935 | E30: 6.5 | F30: =D30*E30 -> 2937.9578 | G30: =+D30-SUM(H30:J30) -> 451.9935 | H30: =+H7 -> 0 | I30: =+I7 -> 0 | J30: =+J7 -> 0
A31: 1.2.3 | B31: =+B8 -> Terminales 30 kV 240 mm2 | C31: =+C8 -> ud | D31: =+D8 -> 6 | E31: =ROUNDUP(220*240/630,0) -> 84 | F31: =D31*E31 -> 504 | G31: =+D31-SUM(H31:J31) -> 5 | H31: =+H8 -> 1 | I31: =+I8 -> 0 | J31: =+J8 -> 0
A32: 1.2.3 | B32: =+B9 -> Terminales 30 kV 630 mm2 | C32: =+C9 -> ud | D32: =+D9 -> 6 | E32: 220 | F32: =D32*E32 -> 1320 | G32: =+D32-SUM(H32:J32) -> -3 | H32: =+H9 -> 9 | I32: =+I9 -> 0 | J32: =+J9 -> 0
A33: 1.2.4 | B33: =+B10 -> Terminales 220 kV | C33: =+C10 -> ud | D33: =+D10 -> 6 | E33: 2600 | F33: =D33*E33 -> 15600 | G33: =+D33-SUM(H33:J33) -> 6 | H33: =+H10 -> 0 | I33: =+I10 -> 0 | J33: =+J10 -> 0
A34: 1.2.5 | B34: =+B11 -> Autoválvulas 220 kV | C34: =+C11 -> ud | D34: =+D11 -> 0 | E34: 1300 | F34: =D34*E34 -> 0 | G34: =+D34-SUM(H34:J34) -> 0 | H34: =+H11 -> 0 | I34: =+I11 -> 0 | J34: =+J11 -> 0
A35: 1.2.6 | B35: =+B12 -> Cámaras de empalmes 30 kV | C35: =+C12 -> ud | D35: =+D12 -> 0 | E35: 400 | F35: =D35*E35 -> 0 | G35: =+D35-SUM(H35:J35) -> 1 | H35: =+H12 -> -1 | I35: =+I12 -> 0 | J35: =+J12 -> 0
A36: 1.2.7 | B36: =+B13 -> Cámaras de empalmes 220 kV | C36: =+C13 -> ud | D36: =+D13 -> 0 | E36: 3100 | F36: =D36*E36 -> 0 | G36: =+D36-SUM(H36:J36) -> 0 | H36: =+H13 -> 0 | I36: =+I13 -> 0 | J36: =+J13 -> 0
A37: 1.2.8 | B37: =+B14 -> Empalmes 30 kV | C37: =+C14 -> ud | D37: =+D14 -> 0 | E37: 300 | F37: =D37*E37 -> 0 | G37: =+D37-SUM(H37:J37) -> 6 | H37: =+H14 -> -6 | I37: =+I14 -> 0 | J37: =+J14 -> 0
A38: 1.2.9 | B38: =+B15 -> Empalmes 220 kV | C38: =+C15 -> ud | D38: =+D15 -> 0 | E38: 2500 | F38: =D38*E38 -> 0 | G38: =+D38-SUM(H38:J38) -> 0 | H38: =+H15 -> 0 | I38: =+I15 -> 0 | J38: =+J15 -> 0
A39: 1.2.10 | B39: =+B16 -> Caja de puesta a tierra 30 kV | C39: =+C16 -> ud | D39: =+D16 -> 0 | E39: 220 | F39: =D39*E39 -> 0 | G39: =+D39-SUM(H39:J39) -> 0 | H39: =+H16 -> 0 | I39: =+I16 -> 0 | J39: =+J16 -> 0
A40: 1.2.11 | B40: =+B17 -> Caja de puesta a tierra 220 kV intemperie | C40: =+C17 -> ud | D40: =+D18 -> 3 | E40: 800 | F40: =D40*E40 -> 2400 | G40: =+D40-SUM(H40:J40) -> 3 | H40: =+H17 -> 0 | I40: =+I17 -> 0 | J40: =+J17 -> 0
A41: 1.2.11 | B41: =+B18 -> Caja de puesta a tierra 220 kV intemperie con descargador | C41: =+C18 -> ud | D41: =+D18 -> 3 | E41: 900 | F41: =D41*E41 -> 2700 | G41: =+D41-SUM(H41:J41) -> 3 | H41: =+H18 -> 0 | I41: =+I18 -> 0 | J41: =+J18 -> 0
A42: 1.2.12 | B42: =+B19 -> Pequeño material p.a.t pantallas | C42: =+C19 -> ud | D42: =+D19 -> 2 | E42: 400 | F42: =D42*E42 -> 800 | G42: =+D42-SUM(H42:J42) -> 0 | H42: =+H19 -> 2 | I42: =+I19 -> 0 | J42: =+J19 -> 0
A43: 1.2.13 | B43: =+B20 -> Cable comunicaciones FO ccto 30 kV | C43: =+C20 -> m | D43: =+D20 -> 4632.6 | E43: 1.9 | F43: =D43*E43 -> 8801.94 | G43: =+D43-SUM(H43:J43) -> 4632.6 | H43: =+'2.- datos subt'!C13 -> 0 | I43: =+'2.- datos subt'!D13 -> 0 | J43: =+'2.- datos subt'!E13 -> 0
A44: 1.2.14 | B44: =+B21 -> Cable comunicaciones FO ccto 220 kV | C44: =+C21 -> m | D44: =+D21 -> 1355.9805 | E44: 2.8 | F44: =D44*E44 -> 3796.7454 | G44: =+D44-SUM(H44:J44) -> 1355.9805 | H44: =+H21 -> 0 | I44: =+I21 -> 0 | J44: =+J21 -> 0
A45: 1.2.15 | B45: =+B22 -> Cajas empalme FO ccto 30 kV | C45: =+C22 -> ud | D45: =+D22 -> 0 | E45: 400 | F45: =D45*E45 -> 0 | G45: =+D45-SUM(H45:J45) -> 0 | H45: =+'2.- datos subt'!C5 -> 0 | I45: =+'2.- datos subt'!D5 -> 0 | J45: =+'2.- datos subt'!E5 -> 0
A46: 1.2.16 | B46: =+B23 -> Cajas empalme FO ccto 220 kV | C46: =+C23 -> ud | D46: =+D23 -> 0 | E46: 600 | F46: =D46*E46 -> 0 | G46: =+D46-SUM(H46:J46) -> 0 | H46: =+H23 -> 0 | I46: =+I23 -> 0 | J46: =+J23 -> 0
A47: TOTAL CAPÍTULO 1.2.- | F47: =SUM(F28:F46) -> 73144.217
A49: CAPÍTULO 1.3. OBRA CIVIL LÍNEA SUBTERRÁNEA
A50: Partida | B50: Concepto | C50: Ud. | D50: Cantidad | E50: Precio Ud | F50: Importe (€)
A51: 1.3.1 | B51: Zanja 30 kV, inlcuyendo excavación, hormigonado, compactado, tubos y señalización. | C51: m | D51: =+'2.- datos subt'!B6-D53 -> 2206 | E51: 24 | F51: =D51*E51 -> 52944 | G51: =+D51-SUM(H51:J51) -> 2206 | H51: =+'2.- datos subt'!C6-H53 -> 0 | I51: =+'2.- datos subt'!D6-I53 -> 0 | J51: =+'2.- datos subt'!E6-J53 -> 0
A52: 1.3.2 | B52: Zanja 220 kV, inlcuyendo excavación, hormigonado, compactado, tubos y señalización. | C52: m | D52: =+'2.- datos subt'!B25 -> 430.47 | E52: 80 | F52: =D52*E52 -> 34437.6 | G52: =+D52-SUM(H52:J52) -> 430.47 | H52: 0 | I52: 0 | J52: 0
A53: 1.3.3 | B53: Perforación horizontal ccto 30 kV | C53: m | D53: =+'2.- datos subt'!B7 -> 0 | E53: 250 | F53: =D53*E53 -> 0 | G53: =+D53-SUM(H53:J53) -> 0 | H53: =+'2.- datos subt'!C7 -> 0 | I53: =+'2.- datos subt'!D7 -> 0 | J53: =+'2.- datos subt'!E7 -> 0
A54: 1.3.4 | B54: Perforación horizontal ccto 220 kV | C54: m | D54: =+'2.- datos subt'!B26 -> 0 | E54: 1300 | F54: =D54*E54 -> 0 | G54: =+D54-SUM(H54:J54) -> 0 | H54: 0 | I54: 0 | J54: 0
A55: 1.3.5 | B55: =+B12 -> Cámaras de empalmes 30 kV | C55: ud | D55: =+'2.- datos subt'!B15 -> 0 | E55: 400 | F55: =D55*E55 -> 0 | G55: =+D55-SUM(H55:J55) -> 6 | H55: =+'2.- datos subt'!C15 -> -6 | I55: =+'2.- datos subt'!D15 -> 0 | J55: =+'2.- datos subt'!E15 -> 0
A56: 1.3.6 | B56: =+B13 -> Cámaras de empalmes 220 kV | C56: ud | D56: =+'2.- datos subt'!B31 -> 0 | E56: 7500 | F56: =D56*E56 -> 0 | G56: =+D56-SUM(H56:J56) -> 0 | H56: 0 | I56: 0 | J56: 0
A57: TOTAL CAPÍTULO 1.3.- | F57: =SUM(F51:F56) -> 87381.6
A58: TOTAL CAPÍTULO 1.- LINEA SUBTERRÁNEA | F58: =+F57+F47+F24 -> 423703.71
A60: CAPÍTULO 2. LÍNEA AÉREA
A61: CAPÍTULO 2.1 MATERIALES LÍNEA AÉREA
A62: Partida | B62: Concepto | C62: Ud. | D62: Cantidad | E62: Precio Ud | F62: Importe (€)
A63: 2.1.1 | B63: Apoyo metálico de celosía de acero galvanizados. | C63: Tn | D63: =+'1.- datos aéreo'!R16 -> 0 | E63: 750 | F63: =D63*E63 -> 0 | G63: =+D63-SUM(H63:J63) -> 0
A64: 2.1.2 | B64: Conductor tipo LA280 cctos 30 kV | C64: kg | D64: =+'1.- datos aéreo'!O50 -> 0 | E64: 1.8 | F64: =D64*E64 -> 0 | G64: =+D64-SUM(H64:J64) -> 0
A65: 2.1.3 | B65: Conductor tipo LA280 cctos 220 kV | C65: kg | D65: =+'1.- datos aéreo'!O51 -> 0 | E65: =+E64 -> 1.8 | F65: =D65*E65 -> 0 | G65: =+D65-SUM(H65:J65) -> 0
A66: 2.1.4 | B66: Conductor tipo LA510 cctos 220 kV | C66: kg | D66: =+'1.- datos aéreo'!O52 -> 0 | E66: =0.8*2.61 -> 2.088 | F66: =D66*E66 -> 0 | G66: =+D66-SUM(H66:J66) -> 0
A67: 2.1.5 | B67: Cable compuesto OPGW cctos 30 kV | C67: m | D67: =+'1.- datos aéreo'!O53 -> 0 | E67: 1.6 | F67: =D67*E67 -> 0 | G67: =+D67-SUM(H67:J67) -> 0
A68: 2.1.6 | B68: Cable compuesto OPGW cctos 220 kV | C68: m | D68: =+'1.- datos aéreo'!O54 -> 0 | E68: =+E67 -> 1.6 | F68: =D68*E68 -> 0 | G68: =+D68-SUM(H68:J68) -> 0
A69: 2.1.7 | B69: Aislador Composite ccto 30 kV DX LA280 | C69: ud | D69: =+'1.- datos aéreo'!O55 -> 0 | E69: 20 | F69: =D69*E69 -> 0 | G69: =+D69-SUM(H69:J69) -> 0
A70: 2.1.8 | B70: Aislador Composite ccto 30 kV DX LA280 en apoyos compartidos 220 kV-ap06-08-14 | C70: ud | D70: =+'1.- datos aéreo'!O56 -> 0 | E70: 65 | F70: =D70*E70 -> 0 | G70: =+D70-SUM(H70:J70) -> 0
A71: 2.1.9 | B71: Aislador Composite ccto 220 kV DX LA280 | C71: ud | D71: =+'1.- datos aéreo'!O57 -> 0 | E71: 85 | F71: =D71*E71 -> 0 | G71: =+D71-SUM(H71:J71) -> 0
A72: 2.1.10 | B72: Aislador Composite ccto 220 kV TX LA510 | C72: ud | D72: =+'1.- datos aéreo'!O58 -> 0 | E72: 101 | F72: =D72*E72 -> 0 | G72: =+D72-SUM(H72:J72) -> 0
A73: 2.1.11 | B73: Cadena suspensión ccto 30 kV DX LA280 | C73: ud | D73: =+'1.- datos aéreo'!O59 -> 0 | E73: 240 | F73: =D73*E73 -> 0 | G73: =+D73-SUM(H73:J73) -> 0
A74: 2.1.12 | B74: Cadena suspensión ccto 30 kV DX LA280 en apoyos compartidos 220 kV-ap06-08-14 | C74: ud | D74: =+'1.- datos aéreo'!O60 -> 0 | E74: =+E73*1.1 -> 264 | F74: =D74*E74 -> 0 | G74: =+D74-SUM(H74:J74) -> 0
A75: 2.1.13 | B75: Cadena suspensión ccto 220 kV DX LA280 | C75: ud | D75: =+'1.- datos aéreo'!O61 -> 0 | E75: =+E74*1.1 -> 290.4 | F75: =D75*E75 -> 0 | G75: =+D75-SUM(H75:J75) -> 0
A76: 2.1.14 | B76: Cadena suspensión ccto 220 kV TX LA510 | C76: ud | D76: =+'1.- datos aéreo'!O62 -> 0 | E76: =+E75*1.3 -> 377.52 | F76: =D76*E76 -> 0 | G76: =+D76-SUM(H76:J76) -> 0
A77: 2.1.15 | B77: Cadena amarre ccto 30 kV DX LA280 | C77: ud | D77: =+'1.- datos aéreo'!O63 -> 0 | E77: 250 | F77: =D77*E77 -> 0 | G77: =+D77-SUM(H77:J77) -> 0
A78: 2.1.16 | B78: Cadena amarre ccto 30 kV DX LA280 en apoyos compartidos 220 kV-ap06-08-14 | C78: ud | D78: =+'1.- datos aéreo'!O64 -> 0 | E78: =+E77*1.1 -> 275 | F78: =D78*E78 -> 0 | G78: =+D78-SUM(H78:J78) -> 0
A79: 2.1.17 | B79: Cadena amarre ccto 220 kV DX LA280 | C79: ud | D79: =+'1.- datos aéreo'!O65 -> 0 | E79: =+E78*1.1 -> 302.5 | F79: =D79*E79 -> 0 | G79: =+D79-SUM(H79:J79) -> 0
A80: 2.1.18 | B80: Cadena amarre ccto 220 kV TX LA510 | C80: ud | D80: =+'1.- datos aéreo'!O66 -> 0 | E80: =+E79*1.3 -> 393.25 | F80: =D80*E80 -> 0 | G80: =+D80-SUM(H80:J80) -> 0
A81: 2.1.19 | B81: Cadena suspensión OPGW ccto 30 kV DX LA280 | C81: ud | D81: =+'1.- datos aéreo'!O67 -> 0 | E81: 40 | F81: =D81*E81 -> 0 | G81: =+D81-SUM(H81:J81) -> 0
A82: 2.1.20 | B82: Cadena suspensión OPGW ccto 220 kV DX LA280 | C82: ud | D82: =+'1.- datos aéreo'!O68 -> 0 | E82: =+E81 -> 40 | F82: =D82*E82 -> 0 | G82: =+D82-SUM(H82:J82) -> 0
A83: 2.1.21 | B83: Cadena suspensión OPGW ccto 220 kV TX LA510 | C83: ud | D83: =+'1.- datos aéreo'!O69 -> 0 | E83: =+E82 -> 40 | F83: =D83*E83 -> 0 | G83: =+D83-SUM(H83:J83) -> 0
A84: 2.1.22 | B84: Cadena amarre OPGW ccto 30 kV DX LA280 | C84: ud | D84: =+'1.- datos aéreo'!O70 -> 0 | E84: =+E81*1.3 -> 52 | F84: =D84*E84 -> 0 | G84: =+D84-SUM(H84:J84) -> 0
A85: 2.1.23 | B85: Cadena amarre OPGW ccto 220 kV DX LA280 | C85: ud | D85: =+'1.- datos aéreo'!O71 -> 0 | E85: =+E84 -> 52 | F85: =D85*E85 -> 0 | G85: =+D85-SUM(H85:J85) -> 0
A86: 2.1.24 | B86: Cadena amarre OPGW ccto 220 kV TX LA510 | C86: ud | D86: =+'1.- datos aéreo'!O72 -> 0 | E86: =+E85 -> 52 | F86: =D86*E86 -> 0 | G86: =+D86-SUM(H86:J86) -> 0
A87: 2.1.25 | B87: Placa Riesgo Eléctrico y señalización | C87: ud | D87: =+'1.- datos aéreo'!O73 -> 0 | E87: 12 | F87: =D87*E87 -> 0 | G87: =+D87-SUM(H87:J87) -> 0
A88: 2.1.26 | B88: Amortiguador separador conductor tipo LA280 cctos 30 kV | C88: ud | D88: =+'1.- datos aéreo'!O74 -> 0 | E88: 12 | F88: =D88*E88 -> 0 | G88: =+D88-SUM(H88:J88) -> 0
A89: 2.1.27 | B89: Amortiguador separador conducto tipo LA280 cctos 220 kV | C89: ud | D89: =+'1.- datos aéreo'!O75 -> 0 | E89: =+E88 -> 12 | F89: =D89*E89 -> 0 | G89: =+D89-SUM(H89:J89) -> 0
A90: 2.1.28 | B90: Amortiguador separador conductor tipo LA510 cctos 220 kV | C90: ud | D90: =+'1.- datos aéreo'!O76 -> 0 | E90: =+E89*2.1 -> 25.2 | F90: =D90*E90 -> 0 | G90: =+D90-SUM(H90:J90) -> 0
A91: 2.1.29 | B91: Amortiguador OPGW ccto 30 kV | C91: ud | D91: =+'1.- datos aéreo'!O77 -> 0 | E91: 12 | F91: =D91*E91 -> 0 | G91: =+D91-SUM(H91:J91) -> 0
A92: 2.1.30 | B92: Amortiguador OPGW ccto 220 kV | C92: ud | D92: =+'1.- datos aéreo'!O78 -> 0 | E92: =+E91 -> 12 | F92: =D92*E92 -> 0 | G92: =+D92-SUM(H92:J92) -> 0
A93: 2.1.31 | B93: Salvapájaros OPGW ccto 30 kV | C93: ud | D93: =+'1.- datos aéreo'!O79 -> 0 | E93: 11 | F93: =D93*E93 -> 0 | G93: =+D93-SUM(H93:J93) -> 0
A94: 2.1.32 | B94: Salvapájaros OPGW ccto 220 kV | C94: ud | D94: =+'1.- datos aéreo'!O80 -> 0 | E94: =+E93 -> 11 | F94: =D94*E94 -> 0 | G94: =+D94-SUM(H94:J94) -> 0
A95: 2.1.33 | B95: PAT apoyo | C95: ud | D95: =+'1.- datos aéreo'!O81 -> 0 | E95: 120 | F95: =D95*E95 -> 0 | G95: =+D95-SUM(H95:J95) -> 0
A96: 2.1.34 | B96: Conexión FO | C96: ud | D96: =+'1.- datos aéreo'!O82 -> 0 | E96: 500 | F96: =D96*E96 -> 0 | G96: =+D96-SUM(H96:J96) -> 0
A97: TOTAL CAPÍTULO 2.1.- | F97: =SUM(F63:F96) -> 0
A99: CAPÍTULO 2.2 MONTAJE LÍNEA AÉREA
A100: Partida | B100: Concepto | C100: Ud. | D100: Cantidad | E100: Precio Ud | F100: Importe (€)
A101: 2.1.1 | B101: =+B63 -> Apoyo metálico de celosía de acero galvanizados. | C101: Tn | D101: =+D63 -> 0 | E101: 200 | F101: =D101*E101 -> 0 | G101: =+D101-SUM(H101:J101) -> 0 | H101: =+H63 -> 0 | I101: =+I63 -> 0 | J101: =+J63 -> 0
A102: 2.1.2 | B102: =+B64 -> Conductor tipo LA280 cctos 30 kV | C102: =+C64 -> kg | D102: =+D64 -> 0 | E102: 1.3 | F102: =D102*E102 -> 0 | G102: =+D102-SUM(H102:J102) -> 0 | H102: =+H64 -> 0 | I102: =+I64 -> 0 | J102: =+J64 -> 0
A103: 2.1.3 | B103: =+B65 -> Conductor tipo LA280 cctos 220 kV | C103: =+C65 -> kg | D103: =+D65 -> 0 | E103: =+E102 -> 1.3 | F103: =D103*E103 -> 0 | G103: =+D103-SUM(H103:J103) -> 0 | H103: =+H65 -> 0 | I103: =+I65 -> 0 | J103: =+J65 -> 0
A104: 2.1.4 | B104: =+B66 -> Conductor tipo LA510 cctos 220 kV | C104: =+C66 -> kg | D104: =+D66 -> 0 | E104: =+E103*1.6 -> 2.08 | F104: =D104*E104 -> 0 | G104: =+D104-SUM(H104:J104) -> 0 | H104: =+H66 -> 0 | I104: =+I66 -> 0 | J104: =+J66 -> 0
...

Sheet PRESUPUESTO  TTMM 1 UBARRUNDIA
A2: CAPÍTULO 1. LÍNEA SUBTERRÁNEA
A3: CAPÍTULO 1.1 MATERIALES LÍNEA SUBTERRÁNEA
A4: Partida | B4: Concepto | C4: Ud. | D4: Cantidad | E4: Precio Ud | F4: Importe (€)
A5: 1.1.1 | B5: Cable aislado 30 kV | C5: m | D5: =+'PRESUPUESTO P'!H5 -> 0 | E5: =+'PRESUPUESTO P'!E5 -> 4 | F5: =D5*E5 -> 0
A6: 1.1.2 | B6: Cable aislado 220 kV | C6: m | D6: =+'PRESUPUESTO P'!H7 -> 0 | E6: =+'PRESUPUESTO P'!E7 -> 120 | F6: =D6*E6 -> 0
A7: 1.1.3 | B7: Terminales 30 kV | C7: ud | D7: =+'PRESUPUESTO P'!H9 -> 9 | E7: =+'PRESUPUESTO P'!E9 -> 160 | F7: =D7*E7 -> 1440
A8: 1.1.4 | B8: Terminales 220 kV | C8: ud | D8: =+'PRESUPUESTO P'!H10 -> 0 | E8: =+'PRESUPUESTO P'!E10 -> 7000 | F8: =D8*E8 -> 0
A9: 1.1.5 | B9: Autoválvulas 220 kV | C9: ud | D9: =+'PRESUPUESTO P'!H11 -> 0 | E9: =+'PRESUPUESTO P'!E11 -> 3300 | F9: =D9*E9 -> 0
A10: 1.1.6 | B10: Cámaras de empalmes 30 kV | C10: ud | D10: =+'PRESUPUESTO P'!H12 -> -1 | E10: =+'PRESUPUESTO P'!E12 -> 300 | F10: =D10*E10 -> -300
A11: 1.1.7 | B11: Cámaras de empalmes 220 kV | C11: ud | D11: =+'PRESUPUESTO P'!H13 -> 0 | E11: =+'PRESUPUESTO P'!E13 -> 950 | F11: =D11*E11 -> 0
A12: 1.1.8 | B12: Empalmes 30 kV | C12: ud | D12: =+'PRESUPUESTO P'!H14 -> -6 | E12: =+'PRESUPUESTO P'!E14 -> 180 | F12: =D12*E12 -> -1080
A13: 1.1.9 | B13: Empalmes 220 kV | C13: ud | D13: =+'PRESUPUESTO P'!H15 -> 0 | E13: =+'PRESUPUESTO P'!E15 -> 5000 | F13: =D13*E13 -> 0
A14: 1.1.10 | B14: Caja de puesta a tierra 30 kV | C14: ud | D14: =+'PRESUPUESTO P'!H16 -> 0 | E14: =+'PRESUPUESTO P'!E16 -> 640 | F14: =D14*E14 -> 0
A15: 1.1.11 | B15: Caja de puesta a tierra 220 kV | C15: ud | D15: =+'PRESUPUESTO P'!H18 -> 0 | E15: =+'PRESUPUESTO P'!E18 -> 3200 | F15: =D15*E15 -> 0
A16: 1.1.12 | B16: Pequeño material p.a.t pantallas | C16: ud | D16: =+'PRESUPUESTO P'!H19 -> 2 | E16: =+'PRESUPUESTO P'!E19 -> 1000 | F16: =D16*E16 -> 2000
A17: 1.1.13 | B17: Cable comunicaciones FO ccto 30 kV | C17: m | D17: =+'PRESUPUESTO P'!H20 -> 0 | E17: =+'PRESUPUESTO P'!E20 -> 1 | F17: =D17*E17 -> 0
A18: 1.1.14 | B18: Cable comunicaciones FO ccto 220 kV | C18: m | D18: =+'PRESUPUESTO P'!H21 -> 0 | E18: =+'PRESUPUESTO P'!E21 -> 1.2 | F18: =D18*E18 -> 0
A19: 1.1.15 | B19: Cajas empalme FO FO ccto 30 kV | C19: ud | D19: =+'PRESUPUESTO P'!H22 -> 0 | E19: =+'PRESUPUESTO P'!E22 -> 300 | F19: =D19*E19 -> 0
A20: 1.1.16 | B20: Cajas empalme FO FO ccto 220 kV | C20: ud | D20: =+'PRESUPUESTO P'!H23 -> 0 | E20: =+'PRESUPUESTO P'!E23 -> 300 | F20: =D20*E20 -> 0
A21: TOTAL CAPÍTULO 1.1.- | F21: =SUM(F5:F20) -> 2060
A23: CAPÍTULO 1.2. MONTAJE LÍNEA SUBTERRÁNEA
A24: Partida | B24: Concepto | C24: Ud. | D24: Cantidad | E24: Precio Ud | F24: Importe (€)
A25: 1.2.1 | B25: =+B5 -> Cable aislado 30 kV | C25: =+C5 -> m | D25: =+D5 -> 0 | E25: =+'PRESUPUESTO P'!E28 -> 1.1 | F25: =D25*E25 -> 0
A26: 1.2.2 | B26: =+B6 -> Cable aislado 220 kV | C26: =+C6 -> m | D26: =+D6 -> 0 | E26: =+'PRESUPUESTO P'!E30 -> 6.5 | F26: =D26*E26 -> 0
A27: 1.2.3 | B27: =+B7 -> Terminales 30 kV | C27: =+C7 -> ud | D27: =+D7 -> 9 | E27: =+'PRESUPUESTO P'!E32 -> 220 | F27: =D27*E27 -> 1980
A28: 1.2.4 | B28: =+B8 -> Terminales 220 kV | C28: =+C8 -> ud | D28: =+D8 -> 0 | E28: =+'PRESUPUESTO P'!E33 -> 2600 | F28: =D28*E28 -> 0
A29: 1.2.5 | B29: =+B9 -> Autoválvulas 220 kV | C29: =+C9 -> ud | D29: =+D9 -> 0 | E29: =+'PRESUPUESTO P'!E34 -> 1300 | F29: =D29*E29 -> 0
A30: 1.2.6 | B30: =+B10 -> Cámaras de empalmes 30 kV | C30: =+C10 -> ud | D30: =+D10 -> -1 | E30: =+'PRESUPUESTO P'!E35 -> 400 | F30: =D30*E30 -> -400
A31: 1.2.7 | B31: =+B11 -> Cámaras de empalmes 220 kV | C31: =+C11 -> ud | D31: =+D11 -> 0 | E31: =+'PRESUPUESTO P'!E36 -> 3100 | F31: =D31*E31 -> 0
A32: 1.2.8 | B32: =+B12 -> Empalmes 30 kV | C32: =+C12 -> ud | D32: =+D12 -> -6 | E32: =+'PRESUPUESTO P'!E37 -> 300 | F32: =D32*E32 -> -1800
A33: 1.2.9 | B33: =+B13 -> Empalmes 220 kV | C33: =+C13 -> ud | D33: =+D13 -> 0 | E33: =+'PRESUPUESTO P'!E38 -> 2500 | F33: =D33*E33 -> 0
A34: 1.2.10 | B34: =+B14 -> Caja de puesta a tierra 30 kV | C34: =+C14 -> ud | D34: =+D14 -> 0 | E34: =+'PRESUPUESTO P'!E39 -> 220 | F34: =D34*E34 -> 0
A35: 1.2.11 | B35: =+B15 -> Caja de puesta a tierra 220 kV | C35: =+C15 -> ud | D35: =+D15 -> 0 | E35: =+'PRESUPUESTO P'!E41 -> 900 | F35: =D35*E35 -> 0
A36: 1.2.12 | B36: =+B16 -> Pequeño material p.a.t pantallas | C36: =+C16 -> ud | D36: =+D16 -> 2 | E36: =+'PRESUPUESTO P'!E42 -> 400 | F36: =D36*E36 -> 800
A37: 1.2.13 | B37: =+B17 -> Cable comunicaciones FO ccto 30 kV | C37: =+C17 -> m | D37: =+D17 -> 0 | E37: =+'PRESUPUESTO P'!E43 -> 1.9 | F37: =D37*E37 -> 0
A38: 1.2.14 | B38: =+B18 -> Cable comunicaciones FO ccto 220 kV | C38: =+C18 -> m | D38: =+D18 -> 0 | E38: =+'PRESUPUESTO P'!E44 -> 2.8 | F38: =D38*E38 -> 0
A39: 1.2.15 | B39: =+B19 -> Cajas empalme FO FO ccto 30 kV | C39: =+C19 -> ud | D39: =+D19 -> 0 | E39: =+'PRESUPUESTO P'!E45 -> 400 | F39: =D39*E39 -> 0
A40: 1.2.16 | B40: =+B20 -> Cajas empalme FO FO ccto 220 kV | C40: =+C20 -> ud | D40: =+D20 -> 0 | E40: =+'PRESUPUESTO P'!E46 -> 600 | F40: =D40*E40 -> 0
A41: TOTAL CAPÍTULO 1.2.- | F41: =SUM(F25:F40) -> 580
A43: CAPÍTULO 1.3. OBRA CIVIL LÍNEA SUBTERRÁNEA
A44: Partida | B44: Concepto | C44: Ud. | D44: Cantidad | E44: Precio Ud | F44: Importe (€)
A45: 1.3.1 | B45: Zanja 30 kV, inlcuyendo excavación, hormigonado, compactado, tubos y señalización. | C45: m | D45: =+'PRESUPUESTO P'!H51 -> 0 | E45: =+'PRESUPUESTO P'!E51 -> 24 | F45: =D45*E45 -> 0
A46: 1.3.2 | B46: Zanja 220 kV, inlcuyendo excavación, hormigonado, compactado, tubos y señalización. | C46: m | D46: =+'PRESUPUESTO P'!H52 -> 0 | E46: =+'PRESUPUESTO P'!E52 -> 80 | F46: =D46*E46 -> 0
A47: 1.3.3 | B47: Perforación horizontal ccto 30 kV | C47: m | D47: =+'PRESUPUESTO P'!H53 -> 0 | E47: =+'PRESUPUESTO P'!E53 -> 250 | F47: =D47*E47 -> 0
A48: 1.3.4 | B48: Perforación horizontal ccto 220 kV | C48: m | D48: =+'PRESUPUESTO P'!H54 -> 0 | E48: =+'PRESUPUESTO P'!E54 -> 1300 | F48: =D48*E48 -> 0
A49: 1.3.5 | B49: =+B10 -> Cámaras de empalmes 30 kV | C49: ud | D49: =+'PRESUPUESTO P'!H55 -> -6 | E49: =+'PRESUPUESTO P'!E55 -> 400 | F49: =D49*E49 -> -2400
A50: 1.3.6 | B50: =+B11 -> Cámaras de empalmes 220 kV | C50: ud | D50: =+'PRESUPUESTO P'!H56 -> 0 | E50: =+'PRESUPUESTO P'!E56 -> 7500 | F50: =D50*E50 -> 0
A51: TOTAL CAPÍTULO 1.3.- | F51: =SUM(F45:F50) -> -2400
A52: TOTAL CAPÍTULO 1.- LINEA SUBTERRÁNEA | F52: =+F51+F41+F21 -> 240
A54: CAPÍTULO 2. LÍNEA AÉREA
A55: CAPÍTULO 2.1 MATERIALES LÍNEA AÉREA
A56: Partida | B56: Concepto | C56: Ud. | D56: Cantidad | E56: Precio Ud | F56: Importe (€)
A57: 2.1.1 | B57: Apoyo metálico de celosia de acero galvanizados. | C57: Tn | D57: =+'PRESUPUESTO P'!H63 -> 0 | E57: =+'PRESUPUESTO P'!E63 -> 750 | F57: =D57*E57 -> 0
A58: 2.1.2 | B58: Conductor tipo LA280 cctos 30 kV | C58: kg | D58: =+'PRESUPUESTO P'!H64 -> 0 | E58: =+'PRESUPUESTO P'!E64 -> 1.8 | F58: =D58*E58 -> 0
A59: 2.1.3 | B59: Conductor tipo LA280 cctos 220 kV | C59: kg | D59: =+'PRESUPUESTO P'!H65 -> 0 | E59: =+'PRESUPUESTO P'!E65 -> 1.8 | F59: =D59*E59 -> 0
A60: 2.1.4 | B60: Conductor tipo LA510 cctos 220 kV | C60: kg | D60: =+'PRESUPUESTO P'!H66 -> 0 | E60: =+'PRESUPUESTO P'!E66 -> 2.088 | F60: =D60*E60 -> 0
A61: 2.1.5 | B61: Cable compuesto OPGW cctos 30 kV | C61: m | D61: =+'PRESUPUESTO P'!H67 -> 0 | E61: =+'PRESUPUESTO P'!E67 -> 1.6 | F61: =D61*E61 -> 0
A62: 2.1.6 | B62: Cable compuesto OPGW cctos 220 kV | C62: m | D62: =+'PRESUPUESTO P'!H68 -> 0 | E62: =+'PRESUPUESTO P'!E68 -> 1.6 | F62: =D62*E62 -> 0
A63: 2.1.7 | B63: Aislador Composite ccto 30 kV DX LA280 | C63: ud | D63: =+'PRESUPUESTO P'!H69 -> 0 | E63: =+'PRESUPUESTO P'!E69 -> 20 | F63: =D63*E63 -> 0
A64: 2.1.8 | B64: Aislador Composite ccto 30 kV DX LA280 en apoyos compartidos 220 kV-ap06-08-14 | C64: ud | D64: =+'PRESUPUESTO P'!H70 -> 0 | E64: =+'PRESUPUESTO P'!E70 -> 65 | F64: =D64*E64 -> 0
A65: 2.1.9 | B65: Aislador Composite ccto 220 kV DX LA280 | C65: ud | D65: =+'PRESUPUESTO P'!H71 -> 0 | E65: =+'PRESUPUESTO P'!E71 -> 85 | F65: =D65*E65 -> 0
A66: 2.1.10 | B66: Aislador Composite ccto 220 kV TX LA510 | C66: ud | D66: =+'PRESUPUESTO P'!H72 -> 0 | E66: =+'PRESUPUESTO P'!E72 -> 101 | F66: =D66*E66 -> 0
A67: 2.1.11 | B67: Cadena suspensión ccto 30 kV DX LA280 | C67: ud | D67: =+'PRESUPUESTO P'!H73 -> 0 | E67: =+'PRESUPUESTO P'!E73 -> 240 | F67: =D67*E67 -> 0
A68: 2.1.12 | B68: Cadena suspensión ccto 30 kV DX LA280 en apoyos compartidos 220 kV-ap06-08-14 | C68: ud | D68: =+'PRESUPUESTO P'!H74 -> 0 | E68: =+'PRESUPUESTO P'!E74 -> 264 | F68: =D68*E68 -> 0
... A90: 2.1.34 | B90: Conexión FO | C90: ud | D90: =+'PRESUPUESTO P'!H96 -> 0 | E90: =+'PRESUPUESTO P'!E96 -> 500 | F90: =D90*E90 -> 0
A91: TOTAL CAPÍTULO 2.1.- | F91: =SUM(F57:F90) -> 0
A93: CAPÍTULO 2.2 MONTAJE LÍNEA AÉREA
A94: Partida | B94: Concepto | C94: Ud. | D94: Cantidad | E94: Precio Ud | F94: Importe (€)
A95: 2.1.1 | B95: =+B57 -> Apoyo metálico de celosia de acero galvanizados. | C95: Tn | D95: =+D57 -> 0 | E95: =+'PRESUPUESTO P'!E101 -> 200 | F95: =D95*E95 -> 0
A96: 2.1.2 | B96: =+B58 -> Conductor tipo LA280 cctos 30 kV | C96: =+C58 -> kg | D96: =+D58 -> 0 | E96: =+'PRESUPUESTO P'!E102 -> 1.3 | F96: =D96*E96 -> 0
A97: 2.1.3 | B97: =+B59 -> Conductor tipo LA280 cctos 220 kV | C97: =+C59 -> kg | D97: =+D59 -> 0 | E97: =+'PRESUPUESTO P'!E103 -> 1.3 | F97: =D97*E97 -> 0
A98: 2.1.4 | B98: =+B60 -> Conductor tipo LA510 cctos 220 kV | C98: =+C60 -> kg | D98: =+D60 -> 0 | E98: =+'PRESUPUESTO P'!E104 -> 2.08 | F98: =D98*E98 -> 0
A99: 2.1.5 | B99: =+B61 -> Cable compuesto OPGW cctos 30 kV | C99: =+C61 -> m | D99: =+D61 -> 0 | E99: =+'PRESUPUESTO P'!E105 -> 2.5 | F99: =D99*E99 -> 0
A100: 2.1.6 | B100: =+B62 -> Cable compuesto OPGW cctos 220 kV | C100: =+C62 -> m | D100: =+D62 -> 0 | E100: =+'PRESUPUESTO P'!E106 -> 2.5 | F100: =D100*E100 -> 0
A101: 2.1.7 | B101: =+B63 -> Aislador Composite ccto 30 kV DX LA280 | C101: =+C63 -> ud | D101: =+D63 -> 0 | E101: =+'PRESUPUESTO P'!E107 -> 43 | F101: =D101*E101 -> 0
A102: 2.1.8 | B102: =+B64 -> Aislador Composite ccto 30 kV DX LA280 en apoyos compartidos 220 kV-ap06-08-14 | C102: =+C64 -> ud | D102: =+D64 -> 0 | E102: =+'PRESUPUESTO P'!E108 -> 47.3 | F102: =D102*E102 -> 0
A103: 2.1.9 | B103: =+B65 -> Aislador Composite ccto 220 kV DX LA280 | C103: =+C65 -> ud | D103: =+D65 -> 0 | E103: =+'PRESUPUESTO P'!E109 -> 52.03 | F103: =D103*E103 -> 0
A104: 2.1.10 | B104: =+B66 -> Aislador Composite ccto 220 kV TX LA510 | C104: =+C66 -> ud | D104: =+D66 -> 0 | E104: =+'PRESUPUESTO P'!E110 -> 67.639 | F104: =D104*E104 -> 0
A105: 2.1.11 | B105: =+B67 -> Cadena suspensión ccto 30 kV DX LA280 | C105: =+C67 -> ud | D105: =+D67 -> 0 | E105: =+'PRESUPUESTO P'!E111 -> 170 | F105: =D105*E105 -> 0
A106: 2.1.12 | B106: =+B68 -> Cadena suspensión ccto 30 kV DX LA280 en apoyos compartidos 220 kV-ap06-08-14 | C106: =+C68 -> ud | D106: =+D68 -> 0 | E106: =+'PRESUPUESTO P'!E112 -> 187 | F106: =D106*E106 -> 0
A107: 2.1.13 | B107: =+B69 -> Cadena suspensión ccto 220 kV DX LA280 | C107: =+C69 -> ud | D107: =+D69 -> 0 | E107: =+'PRESUPUESTO P'!E113 -> 205.7 | F107: =D107*E107 -> 0
... A121: 2.1.27 | B121: =+B83 -> Amortiguador separador conducto tipo LA280 cctos 220 kV | C121: =+C83 -> ud | D121: =+D83 -> 0 | E121: =+'PRESUPUESTO P'!E127 -> 16.8 | F121: =D121*E121 -> 0
A122: 2.1.28 | B122: =+B84 -> Amortiguador separador conductor tipo LA510 cctos 220 kV | C122: =+C86 -> ud | D122: =+D84 -> 0 | E122: =+'PRESUPUESTO P'!E128 -> 35.28 | F122: =D122*E122 -> 0
A123: 2.1.29 | B123: =+B85 -> Amortiguador OPGW ccto 30 kV | C123: =+C87 -> ud | D123: =+D85 -> 0 | E123: =+'PRESUPUESTO P'!E129 -> 16.8 | F123: =D123*E123 -> 0
A124: 2.1.30 | B124: =+B86 -> Amortiguador OPGW ccto 220 kV | C124: =+C88 -> ud | D124: =+D86 -> 0 | E124: =+'PRESUPUESTO P'!E130 -> 16.8 | F124: =D124*E124 -> 0
A125: 2.1.31 | B125: =+B87 -> Salvapajaros OPGW ccto 30 kV | C125: =+C87 -> ud | D125: =+D87 -> 0 | E125: =+'PRESUPUESTO P'!E131 -> 15.4 | F125: =D125*E125 -> 0
A126: 2.1.32 | B126: =+B88 -> Salvapajaros OPGW ccto 220 kV | C126: =+C88 -> ud | D126: =+D88 -> 0 | E126: =+'PRESUPUESTO P'!E132 -> 15.4 | F126: =D126*E126 -> 0
A127: 2.1.33 | B127: =+B89 -> PAT apoyo | C127: =+C89 -> ud | D127: =+D89 -> 0 | E127: =+'PRESUPUESTO P'!E133 -> 300 | F127: =D127*E127 -> 0
A128: 2.1.34 | B128: =+B90 -> Conexión FO | C128: =+C90 -> ud | D128: =+D90 -> 0 | E128: =+'PRESUPUESTO P'!E134 -> 2000 | F128: =D128*E128 -> 0
A129: TOTAL CAPÍTULO 2.2.- | F129: =SUM(F95:F128) -> 0
A131: CAPÍTULO 2.3 OBRA CIVIL LÍNEA AÉREA
A132: Partida | B132: Concepto | C132: Ud. | D132: Cantidad | E132: Precio Ud | F132: Importe (€)
A133: 2.3.1 | B133: Excavación apoyos. Incluye explanación de terreno y retirada de tierras a vertedero autorizado. | C133: m3 | D133: =+'PRESUPUESTO P'!H139 -> 0 | E133: =+'PRESUPUESTO P'!E139 -> 99 | F133: =D133*E133 -> 0
A134: 2.3.2 | B134: Hormigonado de la cimentación de apoyo con hormigón en masa HM-20. Incluye suministro y vertido de hormigón, confección de las peanas, aportación de encofrados normalizados, aportación y colocación del tubo para posterior salida del cable de puesta a tierra. | C134: m3 | D134: =+'PRESUPUESTO P'!H140 -> 0 | E134: =+'PRESUPUESTO P'!E140 -> 102 | F134: =D134*E134 -> 0
A135: 2.3.3 | B135: Ejecución de nuevos accesos a apoyos. Adecuación de accesos existentes y restitución de estos una vez acabado el montaje de los apoyos. | C135: Ud. | D135: =+'PRESUPUESTO P'!H141 -> 0 | E135: =+'PRESUPUESTO P'!E141 -> 200 | F135: =D135*E135 -> 0
A136: TOTAL CAPÍTULO 2.3.- | F136: =SUM(F133:F135) -> 0
A137: TOTAL CAPÍTULO 2.- LÍNEA AÉREA | F137: =+F136+F129+F91 -> 0
A139: CAPÍTULO 3. ESTUDIO DE GESTIÓN DE RESIDUOS
A140: Partida | B140: Concepto | C140: Ud. | D140: Cantidad | E140: Precio Ud | F140: Importe (€)
A141: 3.1.1 | B141: Estudio de Gestión de Residuos | C141: ud | D141: 1 | E141: =+'PRESUPUESTO P'!H147 -> #REF! | F141: =D141*E141 -> #REF!
...

Sheet PRESUPUESTO TTMM 2  ZIGOITIA
A2: CAPÍTULO 1. LÍNEA SUBTERRÁNEA
A3: CAPÍTULO 1.1 MATERIALES LÍNEA SUBTERRÁNEA
A4: Partida | B4: Concepto | C4: Ud. | D4: Cantidad | E4: Precio Ud | F4: Importe (€)
A5: 1.1.1 | B5: Cable aislado 30 kV | C5: m | D5: =+'PRESUPUESTO P'!I5 -> 0 | E5: =+'PRESUPUESTO P'!E5 -> 4 | F5: =D5*E5 -> 0
A6: 1.1.2 | B6: Cable aislado 220 kV | C6: m | D6: =+'PRESUPUESTO P'!I7 -> 0 | E6: =+'PRESUPUESTO P'!E7 -> 120 | F6: =D6*E6 -> 0
A7: 1.1.3 | B7: Terminales 30 kV | C7: ud | D7: =+'PRESUPUESTO P'!I9 -> 0 | E7: =+'PRESUPUESTO P'!E9 -> 160 | F7: =D7*E7 -> 0
A8: 1.1.4 | B8: Terminales 220 kV | C8: ud | D8: =+'PRESUPUESTO P'!I10 -> 0 | E8: =+'PRESUPUESTO P'!E10 -> 7000 | F8: =D8*E8 -> 0
A9: 1.1.5 | B9: Autoválvulas 220 kV | C9: ud | D9: =+'PRESUPUESTO P'!I11 -> 0 | E9: =+'PRESUPUESTO P'!E11 -> 3300 | F9: =D9*E9 -> 0
A10: 1.1.6 | B10: Cámaras de empalmes 30 kV | C10: ud | D10: =+'PRESUPUESTO P'!I12 -> 0 | E10: =+'PRESUPUESTO P'!E12 -> 300 | F10: =D10*E10 -> 0
A11: 1.1.7 | B11: Cámaras de empalmes 220 kV | C11: ud | D11: =+'PRESUPUESTO P'!I13 -> 0 | E11: =+'PRESUPUESTO P'!E13 -> 950 | F11: =D11*E11 -> 0
A12: 1.1.8 | B12: Empalmes 30 kV | C12: ud | D12: =+'PRESUPUESTO P'!I14 -> 0 | E12: =+'PRESUPUESTO P'!E14 -> 180 | F12: =D12*E12 -> 0
A13: 1.1.9 | B13: Empalmes 220 kV | C13: ud | D13: =+'PRESUPUESTO P'!I15 -> 0 | E13: =+'PRESUPUESTO P'!E15 -> 5000 | F13: =D13*E13 -> 0
A14: 1.1.10 | B14: Caja de puesta a tierra 30 kV | C14: ud | D14: =+'PRESUPUESTO P'!I16 -> 0 | E14: =+'PRESUPUESTO P'!E16 -> 640 | F14: =D14*E14 -> 0
A15: 1.1.11 | B15: Caja de puesta a tierra 220 kV | C15: ud | D15: =+'PRESUPUESTO P'!I18 -> 0 | E15: =+'PRESUPUESTO P'!E18 -> 3200 | F15: =D15*E15 -> 0
A16: 1.1.12 | B16: Pequeño material p.a.t pantallas | C16: ud | D16: =+'PRESUPUESTO P'!I19 -> 0 | E16: =+'PRESUPUESTO P'!E19 -> 1000 | F16: =D16*E16 -> 0
A17: 1.1.13 | B17: Cable comunicaciones FO ccto 30 kV | C17: m | D17: =+'PRESUPUESTO P'!I20 -> 0 | E17: =+'PRESUPUESTO P'!E20 -> 1 | F17: =D17*E17 -> 0
A18: 1.1.14 | B18: Cable comunicaciones FO ccto 220 kV | C18: m | D18: =+'PRESUPUESTO P'!I21 -> 0 | E18: =+'PRESUPUESTO P'!E21 -> 1.2 | F18: =D18*E18 -> 0
A19: 1.1.15 | B19: Cajas empalme FO FO ccto 30 kV | C19: ud | D19: =+'PRESUPUESTO P'!I22 -> 0 | E19: =+'PRESUPUESTO P'!E22 -> 300 | F19: =D19*E19 -> 0
A20: 1.1.16 | B20: Cajas empalme FO FO ccto 220 kV | C20: ud | D20: =+'PRESUPUESTO P'!I23 -> 0 | E20: =+'PRESUPUESTO P'!E23 -> 300 | F20: =D20*E20 -> 0
A21: TOTAL CAPÍTULO 1.1.- | F21: =SUM(F5:F20) -> 0
A23: CAPÍTULO 1.2. MONTAJE LÍNEA SUBTERRÁNEA
A24: Partida | B24: Concepto | C24: Ud. | D24: Cantidad | E24: Precio Ud | F24: Importe (€)
A25: 1.2.1 | B25: =+B5 -> Cable aislado 30 kV | C25: =+C5 -> m | D25: =+D5 -> 0 | E25: =+'PRESUPUESTO P'!E28 -> 1.1 | F25: =D25*E25 -> 0
A26: 1.2.2 | B26: =+B6 -> Cable aislado 220 kV | C26: =+C6 -> m | D26: =+D6 -> 0 | E26: =+'PRESUPUESTO P'!E30 -> 6.5 | F26: =D26*E26 -> 0
A27: 1.2.3 | B27: =+B7 -> Terminales 30 kV | C27: =+C7 -> ud | D27: =+D7 -> 0 | E27: =+'PRESUPUESTO P'!E32 -> 220 | F27: =D27*E27 -> 0
A28: 1.2.4 | B28: =+B8 -> Terminales 220 kV | C28: =+C8 -> ud | D28: =+D8 -> 0 | E28: =+'PRESUPUESTO P'!E33 -> 2600 | F28: =D28*E28 -> 0
A29: 1.2.5 | B29: =+B9 -> Autoválvulas 220 kV | C29: =+C9 -> ud | D29: =+D9 -> 0 | E29: =+'PRESUPUESTO P'!E34 -> 1300 | F29: =D29*E29 -> 0
A30: 1.2.6 | B30: =+B10 -> Cámaras de empalmes 30 kV | C30: =+C10 -> ud | D30: =+D10 -> 0 | E30: =+'PRESUPUESTO P'!E35 -> 400 | F30: =D30*E30 -> 0
A31: 1.2.7 | B31: =+B11 -> Cámaras de empalmes 220 kV | C31: =+C11 -> ud | D31: =+D11 -> 0 | E31: =+'PRESUPUESTO P'!E36 -> 3100 | F31: =D31*E31 -> 0
A32: 1.2.8 | B32: =+B12 -> Empalmes 30 kV | C32: =+C12 -> ud | D32: =+D12 -> 0 | E32: =+'PRESUPUESTO P'!E37 -> 300 | F32: =D32*E32 -> 0
A33: 1.2.9 | B33: =+B13 -> Empalmes 220 kV | C33: =+C13 -> ud | D33: =+D13 -> 0 | E33: =+'PRESUPUESTO P'!E38 -> 2500 | F33: =D33*E33 -> 0
A34: 1.2.10 | B34: =+B14 -> Caja de puesta a tierra 30 kV | C34: =+C14 -> ud | D34: =+D14 -> 0 | E34: =+'PRESUPUESTO P'!E39 -> 220 | F34: =D34*E34 -> 0
A35: 1.2.11 | B35: =+B15 -> Caja de puesta a tierra 220 kV | C35: =+C15 -> ud | D35: =+D15 -> 0 | E35: =+'PRESUPUESTO P'!E41 -> 900 | F35: =D35*E35 -> 0
A36: 1.2.12 | B36: =+B16 -> Pequeño material p.a.t pantallas | C36: =+C16 -> ud | D36: =+D16 -> 0 | E36: =+'PRESUPUESTO P'!E42 -> 400 | F36: =D36*E36 -> 0
A37: 1.2.13 | B37: =+B17 -> Cable comunicaciones FO ccto 30 kV | C37: =+C17 -> m | D37: =+D17 -> 0 | E37: =+'PRESUPUESTO P'!E43 -> 1.9 | F37: =D37*E37 -> 0
A38: 1.2.14 | B38: =+B18 -> Cable comunicaciones FO ccto 220 kV | C38: =+C18 -> m | D38: =+D18 -> 0 | E38: =+'PRESUPUESTO P'!E44 -> 2.8 | F38: =D38*E38 -> 0
A39: 1.2.15 | B39: =+B19 -> Cajas empalme FO FO ccto 30 kV | C39: =+C19 -> ud | D39: =+D19 -> 0 | E39: =+'PRESUPUESTO P'!E45 -> 400 | F39: =D39*E39 -> 0
A40: 1.2.16 | B40: =+B20 -> Cajas empalme FO FO ccto 220 kV | C40: =+C20 -> ud | D40: =+D20 -> 0 | E40: =+'PRESUPUESTO P'!E46 -> 600 | F40: =D40*E40 -> 0
A41: TOTAL CAPÍTULO 1.2.- | F41: =SUM(F25:F40) -> 0
A43: CAPÍTULO 1.3. OBRA CIVIL LÍNEA SUBTERRÁNEA
A44: Partida | B44: Concepto | C44: Ud. | D44: Cantidad | E44: Precio Ud | F44: Importe (€)
A45: 1.3.1 | B45: Zanja 30 kV, inlcuyendo excavación, hormigonado, compactado, tubos y señalización. | C45: m | D45: =+'PRESUPUESTO P'!I51 -> 0 | E45: =+'PRESUPUESTO P'!E51 -> 24 | F45: =D45*E45 -> 0
A46: 1.3.2 | B46: Zanja 220 kV, inlcuyendo excavación, hormigonado, compactado, tubos y señalización. | C46: m | D46: =+'PRESUPUESTO P'!I52 -> 0 | E46: =+'PRESUPUESTO P'!E52 -> 80 | F46: =D46*E46 -> 0
A47: 1.3.3 | B47: Perforación horizontal ccto 30 kV | C47: m | D47: =+'PRESUPUESTO P'!I53 -> 0 | E47: =+'PRESUPUESTO P'!E53 -> 250 | F47: =D47*E47 -> 0
A48: 1.3.4 | B48: Perforación horizontal ccto 220 kV | C48: m | D48: =+'PRESUPUESTO P'!I54 -> 0 | E48: =+'PRESUPUESTO P'!E54 -> 1300 | F48: =D48*E48 -> 0
A49: 1.3.5 | B49: =+B10 -> Cámaras de empalmes 30 kV | C49: ud | D49: =+'PRESUPUESTO P'!I55 -> 0 | E49: =+'PRESUPUESTO P'!E55 -> 400 | F49: =D49*E49 -> 0
A50: 1.3.6 | B50: =+B11 -> Cámaras de empalmes 220 kV | C50: ud | D50: =+'PRESUPUESTO P'!I56 -> 0 | E50: =+'PRESUPUESTO P'!E56 -> 7500 | F50: =D50*E50 -> 0
A51: TOTAL CAPÍTULO 1.3.- | F51: =SUM(F45:F50) -> 0
A52: TOTAL CAPÍTULO 1.- LINEA SUBTERRÁNEA | F52: =+F51+F41+F21 -> 0
A54: CAPÍTULO 2. LÍNEA AÉREA
A55: CAPÍTULO 2.1 MATERIALES LÍNEA AÉREA
A56: Partida | B56: Concepto | C56: Ud. | D56: Cantidad | E56: Precio Ud | F56: Importe (€)
A57: 2.1.1 | B57: Apoyo metálico de celosia de acero galvanizados. | C57: Tn | D57: =+'PRESUPUESTO P'!I63 -> 0 | E57: =+'PRESUPUESTO P'!E63 -> 750 | F57: =D57*E57 -> 0
A58: 2.1.2 | B58: Conductor tipo LA280 cctos 30 kV | C58: kg | D58: =+'PRESUPUESTO P'!I64 -> 0 | E58: =+'PRESUPUESTO P'!E64 -> 1.8 | F58: =D58*E58 -> 0
A59: 2.1.3 | B59: Conductor tipo LA280 cctos 220 kV | C59: kg | D59: =+'PRESUPUESTO P'!I65 -> 0 | E59: =+'PRESUPUESTO P'!E65 -> 1.8 | F59: =D59*E59 -> 0
A60: 2.1.4 | B60: Conductor tipo LA510 cctos 220 kV | C60: kg | D60: =+'PRESUPUESTO P'!I66 -> 0 | E60: =+'PRESUPUESTO P'!E66 -> 2.088 | F60: =D60*E60 -> 0
A61: 2.1.5 | B61: Cable compuesto OPGW cctos 30 kV | C61: m | D61: =+'PRESUPUESTO P'!I67 -> 0 | E61: =+'PRESUPUESTO P'!E67 -> 1.6 | F61: =D61*E61 -> 0
A62: 2.1.6 | B62: Cable compuesto OPGW cctos 220 kV | C62: m | D62: =+'PRESUPUESTO P'!I68 -> 0 | E62: =+'PRESUPUESTO P'!E68 -> 1.6 | F62: =D62*E62 -> 0
A63: 2.1.7 | B63: Aislador Composite ccto 30 kV DX LA280 | C63: ud | D63: =+'PRESUPUESTO P'!I69 -> 0 | E63: =+'PRESUPUESTO P'!E69 -> 20 | F63: =D63*E63 -> 0
A64: 2.1.8 | B64: Aislador Composite ccto 30 kV DX LA280 en apoyos compartidos 220 kV-ap06-08-14 | C64: ud | D64: =+'PRESUPUESTO P'!I70 -> 0 | E64: =+'PRESUPUESTO P'!E70 -> 65 | F64: =D64*E64 -> 0
A65: 2.1.9 | B65: Aislador Composite ccto 220 kV DX LA280 | C65: ud | D65: =+'PRESUPUESTO P'!I71 -> 0 | E65: =+'PRESUPUESTO P'!E71 -> 85 | F65: =D65*E65 -> 0
A66: 2.1.10 | B66: Aislador Composite ccto 220 kV TX LA510 | C66: ud | D66: =+'PRESUPUESTO P'!I72 -> 0 | E66: =+'PRESUPUESTO P'!E72 -> 101 | F66: =D66*E66 -> 0
A67: 2.1.11 | B67: Cadena suspensión ccto 30 kV DX LA280 | C67: ud | D67: =+'PRESUPUESTO P'!I73 -> 0 | E67: =+'PRESUPUESTO P'!E73 -> 240 | F67: =D67*E67 -> 0
A68: 2.1.12 | B68: Cadena suspensión ccto 30 kV DX LA280 en apoyos compartidos 220 kV-ap06-08-14 | C68: ud | D68: =+'PRESUPUESTO P'!I74 -> 0 | E68: =+'PRESUPUESTO P'!E74 -> 264 | F68: =D68*E68 -> 0
... A90: 2.1.34 | B90: Conexión FO | C90: ud | D90: =+'PRESUPUESTO P'!I96 -> 0 | E90: =+'PRESUPUESTO P'!E96 -> 500 | F90: =D90*E90 -> 0
A91: TOTAL CAPÍTULO 2.1.- | F91: =SUM(F57:F90) -> 0
A93: CAPÍTULO 2.2 MONTAJE LÍNEA AÉREA
A94: Partida | B94: Concepto | C94: Ud. | D94: Cantidad | E94: Precio Ud | F94: Importe (€)
A95: 2.1.1 | B95: =+B57 -> Apoyo metálico de celosia de acero galvanizados. | C95: Tn | D95: =+D57 -> 0 | E95: =+'PRESUPUESTO P'!E101 -> 200 | F95: =D95*E95 -> 0
A96: 2.1.2 | B96: =+B58 -> Conductor tipo LA280 cctos 30 kV | C96: =+C58 -> kg | D96: =+D58 -> 0 | E96: =+'PRESUPUESTO P'!E102 -> 1.3 | F96: =D96*E96 -> 0
A97: 2.1.3 | B97: =+B59 -> Conductor tipo LA280 cctos 220 kV | C97: =+C59 -> kg | D97: =+D59 -> 0 | E97: =+'PRESUPUESTO P'!E103 -> 1.3 | F97: =D97*E97 -> 0
A98: 2.1.4 | B98: =+B60 -> Conductor tipo LA510 cctos 220 kV | C98: =+C60 -> kg | D98: =+D60 -> 0 | E98: =+'PRESUPUESTO P'!E104 -> 2.08 | F98: =D98*E98 -> 0
A99: 2.1.5 | B99: =+B61 -> Cable compuesto OPGW cctos 30 kV | C99: =+C61 -> m | D99: =+D61 -> 0 | E99: =+'PRESUPUESTO P'!E105 -> 2.5 | F99: =D99*E99 -> 0
A100: 2.1.6 | B100: =+B62 -> Cable compuesto OPGW cctos 220 kV | C100: =+C62 -> m | D100: =+D62 -> 0 | E100: =+'PRESUPUESTO P'!E106 -> 2.5 | F100: =D100*E100 -> 0
A101: 2.1.7 | B101: =+B63 -> Aislador Composite ccto 30 kV DX LA280 | C101: =+C63 -> ud | D101: =+D63 -> 0 | E101: =+'PRESUPUESTO P'!E107 -> 43 | F101: =D101*E101 -> 0
A102: 2.1.8 | B102: =+B64 -> Aislador Composite ccto 30 kV DX LA280 en apoyos compartidos 220 kV-ap06-08-14 | C102: =+C64 -> ud | D102: =+D64 -> 0 | E102: =+'PRESUPUESTO P'!E108 -> 47.3 | F102: =D102*E102 -> 0
A103: 2.1.9 | B103: =+B65 -> Aislador Composite ccto 220 kV DX LA280 | C103: =+C65 -> ud | D103: =+D65 -> 0 | E103: =+'PRESUPUESTO P'!E109 -> 52.03 | F103: =D103*E103 -> 0
A104: 2.1.10 | B104: =+B66 -> Aislador Composite ccto 220 kV TX LA510 | C104: =+C66 -> ud | D104: =+D66 -> 0 | E104: =+'PRESUPUESTO P'!E110 -> 67.639 | F104: =D104*E104 -> 0
A105: 2.1.11 | B105: =+B67 -> Cadena suspensión ccto 30 kV DX LA280 | C105: =+C67 -> ud | D105: =+D67 -> 0 | E105: =+'PRESUPUESTO P'!E111 -> 170 | F105: =D105*E105 -> 0
A106: 2.1.12 | B106: =+B68 -> Cadena suspensión ccto 30 kV DX LA280 en apoyos compartidos 220 kV-ap06-08-14 | C106: =+C68 -> ud | D106: =+D68 -> 0 | E106: =+'PRESUPUESTO P'!E112 -> 187 | F106: =D106*E106 -> 0
A107: 2.1.13 | B107: =+B69 -> Cadena suspensión ccto 220 kV DX LA280 | C107: =+C69 -> ud | D107: =+D69 -> 0 | E107: =+'PRESUPUESTO P'!E113 -> 205.7 | F107: =D107*E107 -> 0
... A121: 2.1.27 | B121: =+B83 -> Amortiguador separador conducto tipo LA280 cctos 220 kV | C121: =+C83 -> ud | D121: =+D83 -> 0 | E121: =+'PRESUPUESTO P'!E127 -> 16.8 | F121: =D121*E121 -> 0
A122: 2.1.28 | B122: =+B84 -> Amortiguador separador conductor tipo LA510 cctos 220 kV | C122: =+C86 -> ud | D122: =+D84 -> 0 | E122: =+'PRESUPUESTO P'!E128 -> 35.28 | F122: =D122*E122 -> 0
A123: 2.1.29 | B123: =+B85 -> Amortiguador OPGW ccto 30 kV | C123: =+C87 -> ud | D123: =+D85 -> 0 | E123: =+'PRESUPUESTO P'!E129 -> 16.8 | F123: =D123*E123 -> 0
A124: 2.1.30 | B124: =+B86 -> Amortiguador OPGW ccto 220 kV | C124: =+C88 -> ud | D124: =+D86 -> 0 | E124: =+'PRESUPUESTO P'!E130 -> 16.8 | F124: =D124*E124 -> 0
A125: 2.1.31 | B125: =+B87 -> Salvapajaros OPGW ccto 30 kV | C125: =+C87 -> ud | D125: =+D87 -> 0 | E125: =+'PRESUPUESTO P'!E131 -> 15.4 | F125: =D125*E125 -> 0
A126: 2.1.32 | B126: =+B88 -> Salvapajaros OPGW ccto 220 kV | C126: =+C88 -> ud | D126: =+D88 -> 0 | E126: =+'PRESUPUESTO P'!E132 -> 15.4 | F126: =D126*E126 -> 0
A127: 2.1.33 | B127: =+B89 -> PAT apoyo | C127: =+C89 -> ud | D127: =+D89 -> 0 | E127: =+'PRESUPUESTO P'!E133 -> 300 | F127: =D127*E127 -> 0
A128: 2.1.34 | B128: =+B90 -> Conexión FO | C128: =+C90 -> ud | D128: =+D90 -> 0 | E128: =+'PRESUPUESTO P'!E134 -> 2000 | F128: =D128*E128 -> 0
A129: TOTAL CAPÍTULO 2.2.- | F129: =SUM(F95:F128) -> 0
A131: CAPÍTULO 2.3 OBRA CIVIL LÍNEA AÉREA
A132: Partida | B132: Concepto | C132: Ud. | D132: Cantidad | E132: Precio Ud | F132: Importe (€)
A133: 2.3.1 | B133: Excavación apoyos. Incluye explanación de terreno y retirada de tierras a vertedero autorizado. | C133: m3 | D133: =+'PRESUPUESTO P'!I139 -> 0 | E133: =+'PRESUPUESTO P'!E139 -> 99 | F133: =D133*E133 -> 0
A134: 2.3.2 | B134: Hormigonado de la cimentación de apoyo con hormigón en masa HM-20. Incluye suministro y vertido de hormigón, confección de las peanas, aportación de encofrados normalizados, aportación y colocación del tubo para posterior salida del cable de puesta a tierra. | C134: m3 | D134: =+'PRESUPUESTO P'!I140 -> 0 | E134: =+'PRESUPUESTO P'!E140 -> 102 | F134: =D134*E134 -> 0
A135: 2.3.3 | B135: Ejecución de nuevos accesos a apoyos. Adecuación de accesos existentes y restitución de estos una vez acabado el montaje de los apoyos. | C135: Ud. | D135: =+'PRESUPUESTO P'!I141 -> 0 | E135: =+'PRESUPUESTO P'!E141 -> 200 | F135: =D135*E135 -> 0
A136: TOTAL CAPÍTULO 2.3.- | F136: =SUM(F133:F135) -> 0
A137: TOTAL CAPÍTULO 2.- LÍNEA AÉREA | F137: =+F136+F129+F91 -> 0
A139: CAPÍTULO 3. ESTUDIO DE GESTIÓN DE RESIDUOS
A140: Partida | B140: Concepto | C140: Ud. | D140: Cantidad | E140: Precio Ud | F140: Importe (€)
A141: 3.1.1 | B141: Estudio de Gestión de Residuos | C141: ud | D141: 1 | E141: =+'PRESUPUESTO P'!I147 -> #REF! | F141: =D141*E141 -> #REF!
...

Sheet PRESUPUESTO TTMM 3 no hay
A2: CAPÍTULO 1. LÍNEA SUBTERRÁNEA
A3: CAPÍTULO 1.1 MATERIALES LÍNEA SUBTERRÁNEA
A4: Partida | B4: Concepto | C4: Ud. | D4: Cantidad | E4: Precio Ud | F4: Importe (€)
A5: 1.1.1 | B5: Cable aislado 30 kV | C5: m | D5: =+'PRESUPUESTO P'!J5 -> 0 | E5: =+'PRESUPUESTO P'!E5 -> 4 | F5: =D5*E5 -> 0
A6: 1.1.2 | B6: Cable aislado 220 kV | C6: m | D6: =+'PRESUPUESTO P'!J7 -> 0 | E6: =+'PRESUPUESTO P'!E7 -> 120 | F6: =D6*E6 -> 0
A7: 1.1.3 | B7: Terminales 30 kV | C7: ud | D7: =+'PRESUPUESTO P'!J9 -> 0 | E7: =+'PRESUPUESTO P'!E9 -> 160 | F7: =D7*E7 -> 0
A8: 1.1.4 | B8: Terminales 220 kV | C8: ud | D8: =+'PRESUPUESTO P'!J10 -> 0 | E8: =+'PRESUPUESTO P'!E10 -> 7000 | F8: =D8*E8 -> 0
A9: 1.1.5 | B9: Autoválvulas 220 kV | C9: ud | D9: =+'PRESUPUESTO P'!J11 -> 0 | E9: =+'PRESUPUESTO P'!E11 -> 3300 | F9: =D9*E9 -> 0
A10: 1.1.6 | B10: Cámaras de empalmes 30 kV | C10: ud | D10: =+'PRESUPUESTO P'!J12 -> 0 | E10: =+'PRESUPUESTO P'!E12 -> 300 | F10: =D10*E10 -> 0
A11: 1.1.7 | B11: Cámaras de empalmes 220 kV | C11: ud | D11: =+'PRESUPUESTO P'!J13 -> 0 | E11: =+'PRESUPUESTO P'!E13 -> 950 | F11: =D11*E11 -> 0
A12: 1.1.8 | B12: Empalmes 30 kV | C12: ud | D12: =+'PRESUPUESTO P'!J14 -> 0 | E12: =+'PRESUPUESTO P'!E14 -> 180 | F12: =D12*E12 -> 0
A13: 1.1.9 | B13: Empalmes 220 kV | C13: ud | D13: =+'PRESUPUESTO P'!J15 -> 0 | E13: =+'PRESUPUESTO P'!E15 -> 5000 | F13: =D13*E13 -> 0
A14: 1.1.10 | B14: Caja de puesta a tierra 30 kV | C14: ud | D14: =+'PRESUPUESTO P'!J16 -> 0 | E14: =+'PRESUPUESTO P'!E16 -> 640 | F14: =D14*E14 -> 0
A15: 1.1.11 | B15: Caja de puesta a tierra 220 kV | C15: ud | D15: =+'PRESUPUESTO P'!J18 -> 0 | E15: =+'PRESUPUESTO P'!E18 -> 3200 | F15: =D15*E15 -> 0
A16: 1.1.12 | B16: Pequeño material p.a.t pantallas | C16: ud | D16: =+'PRESUPUESTO P'!J19 -> 0 | E16: =+'PRESUPUESTO P'!E19 -> 1000 | F16: =D16*E16 -> 0
A17: 1.1.13 | B17: Cable comunicaciones FO ccto 30 kV | C17: m | D17: =+'PRESUPUESTO P'!J20 -> 0 | E17: =+'PRESUPUESTO P'!E20 -> 1 | F17: =D17*E17 -> 0
A18: 1.1.14 | B18: Cable comunicaciones FO ccto 220 kV | C18: m | D18: =+'PRESUPUESTO P'!J21 -> 0 | E18: =+'PRESUPUESTO P'!E21 -> 1.2 | F18: =D18*E18 -> 0
A19: 1.1.15 | B19: Cajas empalme FO FO ccto 30 kV | C19: ud | D19: =+'PRESUPUESTO P'!J22 -> 0 | E19: =+'PRESUPUESTO P'!E22 -> 300 | F19: =D19*E19 -> 0
A20: 1.1.16 | B20: Cajas empalme FO FO ccto 220 kV | C20: ud | D20: =+'PRESUPUESTO P'!J23 -> 0 | E20: =+'PRESUPUESTO P'!E23 -> 300 | F20: =D20*E20 -> 0
A21: TOTAL CAPÍTULO 1.1.- | F21: =SUM(F5:F20) -> 0
A23: CAPÍTULO 1.2. MONTAJE LÍNEA SUBTERRÁNEA
A24: Partida | B24: Concepto | C24: Ud. | D24: Cantidad | E24: Precio Ud | F24: Importe (€)
A25: 1.2.1 | B25: =+B5 -> Cable aislado 30 kV | C25: =+C5 -> m | D25: =+D5 -> 0 | E25: =+'PRESUPUESTO P'!E28 -> 1.1 | F25: =D25*E25 -> 0
A26: 1.2.2 | B26: =+B6 -> Cable aislado 220 kV | C26: =+C6 -> m | D26: =+D6 -> 0 | E26: =+'PRESUPUESTO P'!E30 -> 6.5 | F26: =D26*E26 -> 0
A27: 1.2.3 | B27: =+B7 -> Terminales 30 kV | C27: =+C7 -> ud | D27: =+D7 -> 0 | E27: =+'PRESUPUESTO P'!E32 -> 220 | F27: =D27*E27 -> 0
A28: 1.2.4 | B28: =+B8 -> Terminales 220 kV | C28: =+C8 -> ud | D28: =+D8 -> 0 | E28: =+'PRESUPUESTO P'!E33 -> 2600 | F28: =D28*E28 -> 0
A29: 1.2.5 | B29: =+B9 -> Autoválvulas 220 kV | C29: =+C9 -> ud | D29: =+D9 -> 0 | E29: =+'PRESUPUESTO P'!E34 -> 1300 | F29: =D29*E29 -> 0
A30: 1.2.6 | B30: =+B10 -> Cámaras de empalmes 30 kV | C30: =+C10 -> ud | D30: =+D10 -> 0 | E30: =+'PRESUPUESTO P'!E35 -> 400 | F30: =D30*E30 -> 0
A31: 1.2.7 | B31: =+B11 -> Cámaras de empalmes 220 kV | C31: =+C11 -> ud | D31: =+D11 -> 0 | E31: =+'PRESUPUESTO P'!E36 -> 3100 | F31: =D31*E31 -> 0
A32: 1.2.8 | B32: =+B12 -> Empalmes 30 kV | C32: =+C12 -> ud | D32: =+D12 -> 0 | E32: =+'PRESUPUESTO P'!E37 -> 300 | F32: =D32*E32 -> 0
A33: 1.2.9 | B33: =+B13 -> Empalmes 220 kV | C33: =+C13 -> ud | D33: =+D13 -> 0 | E33: =+'PRESUPUESTO P'!E38 -> 2500 | F33: =D33*E33 -> 0
A34: 1.2.10 | B34: =+B14 -> Caja de puesta a tierra 30 kV | C34: =+C14 -> ud | D34: =+D14 -> 0 | E34: =+'PRESUPUESTO P'!E39 -> 220 | F34: =D34*E34 -> 0
A35: 1.2.11 | B35: =+B15 -> Caja de puesta a tierra 220 kV | C35: =+C15 -> ud | D35: =+D15 -> 0 | E35: =+'PRESUPUESTO P'!E41 -> 900 | F35: =D35*E35 -> 0
A36: 1.2.12 | B36: =+B16 -> Pequeño material p.a.t pantallas | C36: =+C16 -> ud | D36: =+D16 -> 0 | E36: =+'PRESUPUESTO P'!E42 -> 400 | F36: =D36*E36 -> 0
A37: 1.2.13 | B37: =+B17 -> Cable comunicaciones FO ccto 30 kV | C37: =+C17 -> m | D37: =+D17 -> 0 | E37: =+'PRESUPUESTO P'!E43 -> 1.9 | F37: =D37*E37 -> 0
A38: 1.2.14 | B38: =+B18 -> Cable comunicaciones FO ccto 220 kV | C38: =+C18 -> m | D38: =+D18 -> 0 | E38: =+'PRESUPUESTO P'!E44 -> 2.8 | F38: =D38*E38 -> 0
A39: 1.2.15 | B39: =+B19 -> Cajas empalme FO FO ccto 30 kV | C39: =+C19 -> ud | D39: =+D19 -> 0 | E39: =+'PRESUPUESTO P'!E45 -> 400 | F39: =D39*E39 -> 0
A40: 1.2.16 | B40: =+B20 -> Cajas empalme FO FO ccto 220 kV | C40: =+C20 -> ud | D40: =+D20 -> 0 | E40: =+'PRESUPUESTO P'!E46 -> 600 | F40: =D40*E40 -> 0
A41: TOTAL CAPÍTULO 1.2.- | F41: =SUM(F25:F40) -> 0
A43: CAPÍTULO 1.3. OBRA CIVIL LÍNEA SUBTERRÁNEA
A44: Partida | B44: Concepto | C44: Ud. | D44: Cantidad | E44: Precio Ud | F44: Importe (€)
A45: 1.3.1 | B45: Zanja 30 kV, inlcuyendo excavación, hormigonado, compactado, tubos y señalización. | C45: m | D45: =+'PRESUPUESTO P'!J51 -> 0 | E45: =+'PRESUPUESTO P'!E51 -> 24 | F45: =D45*E45 -> 0
A46: 1.3.2 | B46: Zanja 220 kV, inlcuyendo excavación, hormigonado, compactado, tubos y señalización. | C46: m | D46: =+'PRESUPUESTO P'!J52 -> 0 | E46: =+'PRESUPUESTO P'!E52 -> 80 | F46: =D46*E46 -> 0
A47: 1.3.3 | B47: Perforación horizontal ccto 30 kV | C47: m | D47: =+'PRESUPUESTO P'!J53 -> 0 | E47: =+'PRESUPUESTO P'!E53 -> 250 | F47: =D47*E47 -> 0
A48: 1.3.4 | B48: Perforación horizontal ccto 220 kV | C48: m | D48: =+'PRESUPUESTO P'!J54 -> 0 | E48: =+'PRESUPUESTO P'!E54 -> 1300 | F48: =D48*E48 -> 0
A49: 1.3.5 | B49: =+B10 -> Cámaras de empalmes 30 kV | C49: ud | D49: =+'PRESUPUESTO P'!J55 -> 0 | E49: =+'PRESUPUESTO P'!E55 -> 400 | F49: =D49*E49 -> 0
A50: 1.3.6 | B50: =+B11 -> Cámaras de empalmes 220 kV | C50: ud | D50: =+'PRESUPUESTO P'!J56 -> 0 | E50: =+'PRESUPUESTO P'!E56 -> 7500 | F50: =D50*E50 -> 0
A51: TOTAL CAPÍTULO 1.3.- | F51: =SUM(F45:F50) -> 0
A52: TOTAL CAPÍTULO 1.- LINEA SUBTERRÁNEA | F52: =+F51+F41+F21 -> 0
A54: CAPÍTULO 2. LÍNEA AÉREA
A55: CAPÍTULO 2.1 MATERIALES LÍNEA AÉREA
A56: Partida | B56: Concepto | C56: Ud. | D56: Cantidad | E56: Precio Ud | F56: Importe (€)
A57: 2.1.1 | B57: Apoyo metálico de celosia de acero galvanizados. | C57: Tn | D57: =+'PRESUPUESTO P'!J63 -> 0 | E57: =+'PRESUPUESTO P'!E63 -> 750 | F57: =D57*E57 -> 0
A58: 2.1.2 | B58: Conductor tipo LA280 cctos 30 kV | C58: kg | D58: =+'PRESUPUESTO P'!J64 -> 0 | E58: =+'PRESUPUESTO P'!E64 -> 1.8 | F58: =D58*E58 -> 0
A59: 2.1.3 | B59: Conductor tipo LA280 cctos 220 kV | C59: kg | D59: =+'PRESUPUESTO P'!J65 -> 0 | E59: =+'PRESUPUESTO P'!E65 -> 1.8 | F59: =D59*E59 -> 0
A60: 2.1.4 | B60: Conductor tipo LA510 cctos 220 kV | C60: kg | D60: =+'PRESUPUESTO P'!J66 -> 0 | E60: =+'PRESUPUESTO P'!E66 -> 2.088 | F60: =D60*E60 -> 0
A61: 2.1.5 | B61: Cable compuesto OPGW cctos 30 kV | C61: m | D61: =+'PRESUPUESTO P'!J67 -> 0 | E61: =+'PRESUPUESTO P'!E67 -> 1.6 | F61: =D61*E61 -> 0
A62: 2.1.6 | B62: Cable compuesto OPGW cctos 220 kV | C62: m | D62: =+'PRESUPUESTO P'!J68 -> 0 | E62: =+'PRESUPUESTO P'!E68 -> 1.6 | F62: =D62*E62 -> 0
A63: 2.1.7 | B63: Aislador Composite ccto 30 kV DX LA280 | C63: ud | D63: =+'PRESUPUESTO P'!J69 -> 0 | E63: =+'PRESUPUESTO P'!E69 -> 20 | F63: =D63*E63 -> 0
A64: 2.1.8 | B64: Aislador Composite ccto 30 kV DX LA280 en apoyos compartidos 220 kV-ap06-08-14 | C64: ud | D64: =+'PRESUPUESTO P'!J70 -> 0 | E64: =+'PRESUPUESTO P'!E70 -> 65 | F64: =D64*E64 -> 0
A65: 2.1.9 | B65: Aislador Composite ccto 220 kV DX LA280 | C65: ud | D65: =+'PRESUPUESTO P'!J71 -> 0 | E65: =+'PRESUPUESTO P'!E71 -> 85 | F65: =D65*E65 -> 0
A66: 2.1.10 | B66: Aislador Composite ccto 220 kV TX LA510 | C66: ud | D66: =+'PRESUPUESTO P'!J72 -> 0 | E66: =+'PRESUPUESTO P'!E72 -> 101 | F66: =D66*E66 -> 0
A67: 2.1.11 | B67: Cadena suspensión ccto 30 kV DX LA280 | C67: ud | D67: =+'PRESUPUESTO P'!J73 -> 0 | E67: =+'PRESUPUESTO P'!E73 -> 240 | F67: =D67*E67 -> 0
A68: 2.1.12 | B68: Cadena suspensión ccto 30 kV DX LA280 en apoyos compartidos 220 kV-ap06-08-14 | C68: ud | D68: =+'PRESUPUESTO P'!J74 -> 0 | E68: =+'PRESUPUESTO P'!E74 -> 264 | F68: =D68*E68 -> 0
... A90: 2.1.34 | B90: Conexión FO | C90: ud | D90: =+'PRESUPUESTO P'!J96 -> 0 | E90: =+'PRESUPUESTO P'!E96 -> 500 | F90: =D90*E90 -> 0
A91: TOTAL CAPÍTULO 2.1.- | F91: =SUM(F57:F90) -> 0
A93: CAPÍTULO 2.2 MONTAJE LÍNEA AÉREA
A94: Partida | B94: Concepto | C94: Ud. | D94: Cantidad | E94: Precio Ud | F94: Importe (€)
A95: 2.1.1 | B95: =+B57 -> Apoyo metálico de celosia de acero galvanizados. | C95: Tn | D95: =+D57 -> 0 | E95: =+'PRESUPUESTO P'!E101 -> 200 | F95: =D95*E95 -> 0
A96: 2.1.2 | B96: =+B58 -> Conductor tipo LA280 cctos 30 kV | C96: =+C58 -> kg | D96: =+D58 -> 0 | E96: =+'PRESUPUESTO P'!E102 -> 1.3 | F96: =D96*E96 -> 0
A97: 2.1.3 | B97: =+B59 -> Conductor tipo LA280 cctos 220 kV | C97: =+C59 -> kg | D97: =+D59 -> 0 | E97: =+'PRESUPUESTO P'!E103 -> 1.3 | F97: =D97*E97 -> 0
A98: 2.1.4 | B98: =+B60 -> Conductor tipo LA510 cctos 220 kV | C98: =+C60 -> kg | D98: =+D60 -> 0 | E98: =+'PRESUPUESTO P'!E104 -> 2.08 | F98: =D98*E98 -> 0
A99: 2.1.5 | B99: =+B61 -> Cable compuesto OPGW cctos 30 kV | C99: =+C61 -> m | D99: =+D61 -> 0 | E99: =+'PRESUPUESTO P'!E105 -> 2.5 | F99: =D99*E99 -> 0
A100: 2.1.6 | B100: =+B62 -> Cable compuesto OPGW cctos 220 kV | C100: =+C62 -> m | D100: =+D62 -> 0 | E100: =+'PRESUPUESTO P'!E106 -> 2.5 | F100: =D100*E100 -> 0
A101: 2.1.7 | B101: =+B63 -> Aislador Composite ccto 30 kV DX LA280 | C101: =+C63 -> ud | D101: =+D63 -> 0 | E101: =+'PRESUPUESTO P'!E107 -> 43 | F101: =D101*E101 -> 0
A102: 2.1.8 | B102: =+B64 -> Aislador Composite ccto 30 kV DX LA280 en apoyos compartidos 220 kV-ap06-08-14 | C102: =+C64 -> ud | D102: =+D64 -> 0 | E102: =+'PRESUPUESTO P'!E108 -> 47.3 | F102: =D102*E102 -> 0
A103: 2.1.9 | B103: =+B65 -> Aislador Composite ccto 220 kV DX LA280 | C103: =+C65 -> ud | D103: =+D65 -> 0 | E103: =+'PRESUPUESTO P'!E109 -> 52.03 | F103: =D103*E103 -> 0
A104: 2.1.10 | B104: =+B66 -> Aislador Composite ccto 220 kV TX LA510 | C104: =+C66 -> ud | D104: =+D66 -> 0 | E104: =+'PRESUPUESTO P'!E110 -> 67.639 | F104: =D104*E104 -> 0
A105: 2.1.11 | B105: =+B67 -> Cadena suspensión ccto 30 kV DX LA280 | C105: =+C67 -> ud | D105: =+D67 -> 0 | E105: =+'PRESUPUESTO P'!E111 -> 170 | F105: =D105*E105 -> 0
A106: 2.1.12 | B106: =+B68 -> Cadena suspensión ccto 30 kV DX LA280 en apoyos compartidos 220 kV-ap06-08-14 | C106: =+C68 -> ud | D106: =+D68 -> 0 | E106: =+'PRESUPUESTO P'!E112 -> 187 | F106: =D106*E106 -> 0
A107: 2.1.13 | B107: =+B69 -> Cadena suspensión ccto 220 kV DX LA280 | C107: =+C69 -> ud | D107: =+D69 -> 0 | E107: =+'PRESUPUESTO P'!E113 -> 205.7 | F107: =D107*E107 -> 0
... A121: 2.1.27 | B121: =+B83 -> Amortiguador separador conducto tipo LA280 cctos 220 kV | C121: =+C83 -> ud | D121: =+D83 -> 0 | E121: =+'PRESUPUESTO P'!E127 -> 16.8 | F121: =D121*E121 -> 0
A122: 2.1.28 | B122: =+B84 -> Amortiguador separador conductor tipo LA510 cctos 220 kV | C122: =+C86 -> ud | D122: =+D84 -> 0 | E122: =+'PRESUPUESTO P'!E128 -> 35.28 | F122: =D122*E122 -> 0
A123: 2.1.29 | B123: =+B85 -> Amortiguador OPGW ccto 30 kV | C123: =+C87 -> ud | D123: =+D85 -> 0 | E123: =+'PRESUPUESTO P'!E129 -> 16.8 | F123: =D123*E123 -> 0
A124: 2.1.30 | B124: =+B86 -> Amortiguador OPGW ccto 220 kV | C124: =+C88 -> ud | D124: =+D86 -> 0 | E124: =+'PRESUPUESTO P'!E130 -> 16.8 | F124: =D124*E124 -> 0
A125: 2.1.31 | B125: =+B87 -> Salvapájaros OPGW ccto 30 kV | C125: =+C87 -> ud | D125: =+D87 -> 0 | E125: =+'PRESUPUESTO P'!E131 -> 15.4 | F125: =D125*E125 -> 0
A126: 2.1.32 | B126: =+B88 -> Salvapájaros OPGW ccto 220 kV | C126: =+C88 -> ud | D126: =+D88 -> 0 | E126: =+'PRESUPUESTO P'!E132 -> 15.4 | F126: =D126*E126 -> 0
A127: 2.1.33 | B127: =+B89 -> PAT apoyo | C127: =+C89 -> ud | D127: =+D89 -> 0 | E127: =+'PRESUPUESTO P'!E133 -> 300 | F127: =D127*E127 -> 0
A128: 2.1.34 | B128: =+B90 -> Conexión FO | C128: =+C90 -> ud | D128: =+D90 -> 0 | E128: =+'PRESUPUESTO P'!E134 -> 2000 | F128: =D128*E128 -> 0
A129: TOTAL CAPÍTULO 2.2.- | F129: =SUM(F95:F128) -> 0
A131: CAPÍTULO 2.3 OBRA CIVIL LÍNEA AÉREA
A132: Partida | B132: Concepto | C132: Ud. | D132: Cantidad | E132: Precio Ud | F132: Importe (€)
A133: 2.3.1 | B133: Excavación apoyos. Incluye explanación de terreno y retirada de tierras a vertedero autorizado. | C133: m3 | D133: =+'PRESUPUESTO P'!J139 -> 0 | E133: =+'PRESUPUESTO P'!E139 -> 99 | F133: =D133*E133 -> 0
A134: 2.3.2 | B134: Hormigonado de la cimentación de apoyo con hormigón en masa HM-20. Incluye suministro y vertido de hormigón, confección de las peanas, aportación de encofrados normalizados, aportación y colocación del tubo para posterior salida del cable de puesta a tierra. | C134: m3 | D134: =+'PRESUPUESTO P'!J140 -> 0 | E134: =+'PRESUPUESTO P'!E140 -> 102 | F134: =D134*E134 -> 0
A135: 2.3.3 | B135: Ejecución de nuevos accesos a apoyos. Adecuación de accesos existentes y restitución de estos una vez acabado el montaje de los apoyos. | C135: Ud. | D135: =+'PRESUPUESTO P'!J141 -> 0 | E135: =+'PRESUPUESTO P'!E141 -> 200 | F135: =D135*E135 -> 0
A136: TOTAL CAPÍTULO 2.3.- | F136: =SUM(F133:F135) -> 0
A137: TOTAL CAPÍTULO 2.- LÍNEA AÉREA | F137: =+F136+F129+F91 -> 0
A139: CAPÍTULO 3. ESTUDIO DE GESTIÓN DE RESIDUOS
A140: Partida | B140: Concepto | C140: Ud. | D140: Cantidad | E140: Precio Ud | F140: Importe (€)
A141: 3.1.1 | B141: Estudio de Gestión de Residuos | C141: ud | D141: 1 | E141: =+'PRESUPUESTO P'!J147 -> #REF! | F141: =D141*E141 -> #REF!
...

Sheet EGR 1-copiar en word 0 EGR
B2: GESTION DE RESIDUOS DE CONSTRUCCIÓN Y DEMOLICIÓN (RCD)
B4: Estimación de residuos en OBRA NUEVA: | C4: ZANJAS BT-MT-AT | H4: Para zanjas nuevas suponemos que un 20% de la tierra no se reutiliza en tapar la zanja, y que de éste 20% un 10% es de residuos Nivel II.
B6: Longitud de zanjas | C6: 0 | D6: m
B7: Ancho de zanjas | C7: 0 | D7: m
B8: Profundidad de zanjas | C8: 0 | D8: m
B9: Volumen total de zanjas | C9: =C6*C7*C8 -> 0 | D9: m²
B10: Volumen total de residuos | C10: =0.2*C9 -> 0 | D10: m³
B11: Volumen de tierras sobrantes | C11: =0.9*C10 -> 0 | D11: m³
B12: Volumen de RCDs Nivel II | C12: =0.1*C10 -> 0 | D12: m³
B15: Estimación de residuos en OBRA NUEVA: | C15: ZANJAS BT-MT-AT | G15: 30 kV
B17: Longitud de zanjas | C17: =+'2.- datos subt'!B6 -> 2206 | D17: m
B18: Ancho de zanjas | C18: 1.356 | D18: m
B19: Profundidad de zanjas | C19: 1.47 | D19: m
B20: Volumen total de zanjas | C20: =C17*C18*C19 -> 4397.2639 | D20: m²
B21: Volumen total de residuos | C21: =0.2*C20 -> 879.45278 | D21: m³
B22: Volumen de tierras sobrantes | C22: =0.9*C21 -> 791.50751 | D22: m³
B23: Volumen de RCDs Nivel II | C23: =0.1*C21 -> 87.945278 | D23: m³
B26: Estimación de residuos en OBRA NUEVA: | C26: ZANJAS BT-MT-AT | G26: 220 kV
B28: Longitud de zanjas | C28: =+'2.- datos subt'!B25 -> 430.47 | D28: m
B29: Ancho de zanjas | C29: 1.2 | D29: m
B30: Profundidad de zanjas | C30: 1.825 | D30: m
B31: Volumen total de zanjas | C31: =C28*C29*C30 -> 942.7293 | D31: m²
B32: Volumen total de residuos | C32: =0.2*C31 -> 188.54586 | D32: m³
B33: Volumen de tierras sobrantes | C33: =0.9*C32 -> 169.69127 | D33: m³
B34: Volumen de RCDs Nivel II | C34: =0.1*C32 -> 18.854586 | D34: m³
B37: Estimación de residuos en OBRA NUEVA: | C37: ZANJAS BT-MT-AT
B39: Longitud de zanjas | C39: 0 | D39: m
B40: Ancho de zanjas | C40: 0 | D40: m
B41: Profundidad de zanjas | C41: 0 | D41: m
B42: Volumen total de zanjas | C42: =C39*C40*C41 -> 0 | D42: m²
B43: Volumen total de residuos | C43: =0.2*C42 -> 0 | D43: m³
B44: Volumen de tierras sobrantes | C44: =0.9*C43 -> 0 | D44: m³
B45: Volumen de RCDs Nivel II | C45: =0.1*C43 -> 0 | D45: m³
B48: Estimación de residuos en OBRA NUEVA: | C48: CÁMARAS DE EMPALME | H48: Para arquetas suponemos que un 80% de la tierra no se reutiliza en tapar la zanja, y que de éste 80% un 10% es de residuos Nivel II.
B50: Numero de cámaras de empalme | C50: =+'2.- datos subt'!B14+'2.- datos subt'!B31 -> 0 | D50: ud
B51: Longitud de la cámara de empalme | C51: 14 | D51: m
B52: Ancho de la cámara de empalme | C52: 3 | D52: m
B53: Profundidad de la cámara de empalme | C53: 2 | D53: m
B54: Volumen total de las cámaras de empalme | C54: =C50*C51*C53*C52 -> 0 | D54: m³
B55: Volumen total de residuos | C55: =0.8*C54 -> 0 | D55: m³
B56: Volumen de tierras sobrantes | C56: =0.9*C55 -> 0 | D56: m³
B57: Volumen de RCDs Nivel II | C57: =0.1*C55 -> 0 | D57: m³
B60: Estimación de residuos en OBRA NUEVA: | C60: APOYOS BT-MT-AT | H60: En apoyos suponemos que el 90% de las tierras no se reutilizan y que de éste 90% un 10% es de residuos Nivel II.
B62: Volumen total cimentación apoyos | C62: =+'1.- datos aéreo'!T16 -> 0 | D62: m³
B63: Volumen total de residuos | C63: =0.9*C62 -> 0 | D63: m³
B64: Volumen de tierras sobrantes | C64: =0.9*C63 -> 0 | D64: m³
B65: Volumen de RCDs Nivel II | C65: =0.1*C64 -> 0 | D65: m³
B68: Estimación de residuos en OBRA NUEVA: | C68: NUEVOS CDs | H68: En nuevos CDs suponemos que el 90% de las tierras no se reutilizan y que de éste 90% un 10% es de residuos Nivel II.
B70: Longitud de excavación | C70: 0 | D70: m
B71: Ancho de excavación | C71: 0 | D71: m
B72: Profundidad de excavación | C72: 0 | D72: m
B73: Volumen total de excavación | C73: =C70*C71*C72 -> 0 | D73: m²
B74: Volumen total de residuos | C74: =0.9*C73 -> 0 | D74: m³
B75: Volumen de tierras sobrantes | C75: =0.9*C74 -> 0 | D75: m³
B76: Volumen de RCDs Nivel II | C76: =0.1*C74 -> 0 | D76: m³
B79: Estimación de residuos en OBRA NUEVA: | C79: REFORMA CDs | H79: En reformas de CDs estimamos el volumen total de residuos directamente, según m3 de escombros
B81: Volumen total de residuos | C81: 0 | D81: m³
B82: Volumen de tierras sobrantes | C82: =0.9*C81 -> 0 | D82: m³
B83: Volumen de RCDs Nivel II | C83: =0.1*C81 -> 0 | D83: m³
B86: Estimación de residuos en OBRA NUEVA: | C86: TOPOS/PHD | H86: Para los pozos de arranque suponemos que un 30% de la tierra de los pozos no se reutiliza, y que de éste 30% un 10% es de residuos Nivel II. Para la perforación dirigida suponemos que un 100% de la tierra de los pozos no se reutiliza, y que de éste 100% un 10% es de residuos Nivel II.
B88: Longitud de pozos | C88: 4 | D88: m
B89: Ancho de pozos | C89: 4 | D89: m
B90: Profundidad de pozos | C90: 2 | D90: m
B91: Volumen total de pozos | C91: =C88*C89*C90*('2.- datos subt'!$B$8+'2.- datos subt'!$B$27) -> 0 | D91: m²
B92: Longitud del topo | C92: =+'2.- datos subt'!B7+'2.- datos subt'!B26 -> 0 | D92: m
B93: Diámetro del topo | C93: 0.71 | D93: m
B94: Volumen total del topo | C94: =C92*(C93/2)^2*PI() -> 0 | D94: m³
B95: Volumen total de residuos | C95: =0.3*C91+C94 -> 0 | D95: m³
B96: Volumen de tierras sobrantes | C96: =0.9*C95 -> 0 | D96: m³
B97: Volumen de RCDs Nivel II | C97: =0.1*C95 -> 0 | D97: m³
B100: Estimación de residuos en OBRA NUEVA: | C100: DEMOLICION DE TABIQUES | H100: Estimamos el volumen total de residuos directamente, según m3 de escombros (100% RCDs Nivel II)
B102: Volumen total de residuos | C102: 0 | D102: m³
B103: Volumen de tierras sobrantes | C103: =0*C102 -> 0 | D103: m³
B104: Volumen de RCDs Nivel II | C104: =1*C102 -> 0 | D104: m³

Sheet EGR2 2--copiar en word 1 EGR
B2: GESTION DE RESIDUOS DE CONSTRUCCIÓN Y DEMOLICIÓN (RCD)
B4: Estimación de residuos Total:
B6: Volumen total de resíduos Nivel II | C6: ='EGR 1-copiar en word 0 EGR'!C12+'EGR 1-copiar en word 0 EGR'!C23+'EGR 1-copiar en word 0 EGR'!C34+'EGR 1-copiar en word 0 EGR'!C45+'EGR 1-copiar en word 0 EGR'!C57+'EGR 1-copiar en word 0 EGR'!C65+'EGR 1-copiar en word 0 EGR'!C76+'EGR 1-copiar en word 0 EGR'!C83+'EGR 1-copiar en word 0 EGR'!C97+'EGR 1-copiar en word 0 EGR'!C104 -> 106.79986 | D6: m³
B7: Densidad tipo (entre 0,5 y 1,5 T/m³) | C7: 1.1 | D7: Tm/m³
B8: Toneladas de residuos Nivel II | C8: =C6*C7 -> 117.47985 | D8: Tm
B10: Volumen de tierras sobrantes Nivel I | C10: ='EGR 1-copiar en word 0 EGR'!C11+'EGR 1-copiar en word 0 EGR'!C22+'EGR 1-copiar en word 0 EGR'!C33++'EGR 1-copiar en word 0 EGR'!C44+'EGR 1-copiar en word 0 EGR'!C56+'EGR 1-copiar en word 0 EGR'!C64+'EGR 1-copiar en word 0 EGR'!C75+'EGR 1-copiar en word 0 EGR'!C82+'EGR 1-copiar en word 0 EGR'!C96+'EGR 1-copiar en word 0 EGR'!C103 -> 961.19878 | D10: m³
B11: Presupuesto estimado de la obra | C11: =+'PRESUPUESTO P'!C160+'PRESUPUESTO P'!C165 -> 423703.71 | D11: €
B12: Presupuesto de movimiento de tierras en proyecto | C12: =0.015*C11 -> 6355.5556 | D12: €
B14: A.1.: RCDs Nivel I
D15: Tm | E15: d | F15: V
B16: Evaluación teórica del peso por tipología de RDC | D16: Toneladas de RDC | E16: Densidad tipo (entre 1,5 y 0,5) | F16: m³ Volumen de Tierras
B17: 1. TIERRAS Y PÉTREOS DE LA EXCAVACIÓN
B18: Tierras y pétreos procedentes de la excavación estimados directamente desde los datos de proyecto | D18: =F18*E18 -> 1441.7982 | E18: 1.5 | F18: =C10 -> 961.19878
B20: A.2.: RCDs Nivel II
C21: % | D21: Tm | E21: d | F21: V
B22: Evaluación teórica del peso por tipología de RDC | C22: % de peso | D22: Toneladas de cada tipo de RDC | E22: Densidad tipo (entre 1,5 y 0,5) | F22: m³ Volumen de Residuos
B23: RCD: Naturaleza no pétrea
B24: 1. Asfalto | C24: 0.05 | D24: =$C$8*C24 -> 5.8739925 | E24: 1.3 | F24: =D24/E24 -> 4.5184558
B25: 2. Madera | C25: 0.04 | D25: =$C$8*C25 -> 4.699194 | E25: 0.6 | F25: =D25/E25 -> 7.8319901
B26: 3. Metales | C26: 0.025 | D26: =$C$8*C26 -> 2.9369963 | E26: 1.5 | F26: =D26/E26 -> 1.9579975
B27: 4. Papel | C27: 0.003 | D27: =$C$8*C27 -> 0.35243955 | E27: 0.9 | F27: =D27/E27 -> 0.3915995
B28: 5. Plástico | C28: 0.015 | D28: =$C$8*C28 -> 1.7621978 | E28: 0.9 | F28: =D28/E28 -> 1.9579975
B29: 6. Vidrio | C29: 0.005 | D29: =$C$8*C29 -> 0.58739925 | E29: 1.5 | F29: =D29/E29 -> 0.3915995
B30: 7. Yeso | C30: 0.002 | D30: =$C$8*C30 -> 0.2349597 | E30: 1.2 | F30: =D30/E30 -> 0.19579975
B31: TOTAL estimación | C31: =SUM(C24:C30) -> 0.14 | D31: =$C$8*C31 -> 16.447179 | F31: =SUM(F24:F30) -> 17.24544
B33: RCD: Naturaleza pétrea
B34: 1. Arena Grava y otros áridos | C34: 0.04 | D34: =$C$8*C34 -> 4.699194 | E34: 1.5 | F34: =D34/E34 -> 3.132796
B35: 2. Hormigón | C35: 0.12 | D35: =$C$8*C35 -> 14.097582 | E35: 1.5 | F35: =D35/E35 -> 9.3983881
B36: 3. Ladrillos , azulejos y otros cerámicos | C36: 0.54 | D36: =$C$8*C36 -> 63.439119 | E36: 1.5 | F36: =D36/E36 -> 42.292746
B37: 4. Piedra | C37: 0.05 | D37: =$C$8*C37 -> 5.8739925 | E37: 1.5 | F37: =D37/E37 -> 3.915995
B38: TOTAL estimación | C38: =SUM(C34:C37) -> 0.75 | D38: =$C$8*C38 -> 88.109888 | F38: =SUM(F34:F37) -> 58.739925
B40: RCD: Potencialmente peligrosos y otros
B41: 1. Basuras | C41: 0.07 | D41: =$C$8*C41 -> 8.2235896 | E41: 0.9 | F41: =D41/E41 -> 9.1373217
B42: 2. Potencialmente peligrosos y otros | C42: 0.04 | D42: =$C$8*C42 -> 4.699194 | E42: 0.5 | F42: =D42/E42 -> 9.3983881
B43: TOTAL estimación | C43: =C41+C42 -> 0.11 | D43: =$C$8*C43 -> 12.922784 | F43: =SUM(F41:F42) -> 18.53571
C44: =C31+C38+C43 -> 1 | D44: =D31+D38+D43 -> 117.47985

Sheet EGR 3-copiar en word 2 EGR
B2: A.1.: RCDs Nivel I
C4: 1. TIERRAS Y PÉTROS DE LA EXCAVACIÓN | F4: Tratamiento | G4: Destino | H4: Cantidad | J4: Porcentajes estimados | M4: esta tabla de copia y pega en la memoria
B5: x | C5: 17 05 04 | D5: Tierras y piedras distintas de las especificadas en el código 17 05 03 | F5: Sin tratamiento esp. | G5: Restauración / Vertedero | H5: =IF(B5="X",'EGR2 2--copiar en word 1 EGR'!D18-H6-H7,0) -> 1441.7982 | J5: Diferencia tipo RCD
C6: 17 05 06 | D6: Lodos de drenaje distintos de los especificados en el código 17 05 06 | F6: Sin tratamiento esp. | G6: Restauración / Vertedero | H6: =IF(B6="X",J6*'EGR2 2--copiar en word 1 EGR'!$D$18,0) -> 0 | J6: 0.15
C7: 17 05 08 | D7: Balasto de vías férreas distinto del especificado en el código 17 05 07 | F7: Sin tratamiento esp. | G7: Restauración / Vertedero | H7: =IF(B7="X",J7*'EGR2 2--copiar en word 1 EGR'!$D$18,0) -> 0 | J7: 0.05
B9: A.2.: RCDs Nivel II
C11: RCD: Naturaleza no pétrea | F11: Tratamiento | G11: Destino | H11: Cantidad
C13: 1. Asfalto
B14: x | C14: 17 03 02 | D14: Mezclas bituminosas distintas a las del código 17 03 01 | F14: Reciclado | G14: Planta de reciclaje RCD | H14: ='EGR2 2--copiar en word 1 EGR'!D24 -> 5.8739925 | J14: Total tipo RCD
C15: 2. Madera
B16: x | C16: 17 02 01 | D16: Madera | F16: Reciclado | G16: Gestor autorizado RNPs | H16: ='EGR2 2--copiar en word 1 EGR'!D25 -> 4.699194 | J16: Total tipo RCD
C17: 3. Metales
B18: x | C18: 17 04 01 | D18: Cobre, bronce, latón | F18: Reciclado | G18: Gestor autorizado RNPs | H18: =IF(B18="X",J18*'EGR2 2--copiar en word 1 EGR'!D26,0) -> 0.29369963 | J18: 0.1
B19: x | C19: 17 04 02 | D19: Aluminio | F19: Reciclado | H19: =IF(B19="X",J19*'EGR2 2--copiar en word 1 EGR'!D27,0) -> 0.024670769 | J19: 0.07
C20: 17 04 03 | D20: Plomo | H20: =IF(B20="X",J20*'EGR2 2--copiar en word 1 EGR'!D28,0) -> 0 | J20: 0.05
C21: 17 04 04 | D21: Zinc | H21: =IF(B21="X",J21*'EGR2 2--copiar en word 1 EGR'!D29,0) -> 0 | J21: 0.15
B22: x | C22: 17 04 05 | D22: Hierro y Acero | F22: Reciclado | H22: =IF(B22="X",'EGR2 2--copiar en word 1 EGR'!D34-H18-H19-H20-H21-H23-H24-H25,0) -> 4.3808236 | J22: Diferencia tipo RCD
C23: 17 04 06 | D23: Estaño | H23: =IF(B23="X",J23*'EGR2 2--copiar en word 1 EGR'!D31,0) -> 0 | J23: 0.1
C24: 17 04 06 | D24: Metales mezclados | F24: Reciclado | H24: =IF(B24="X",J24*'EGR2 2--copiar en word 1 EGR'!D32,0) -> 0 | J24: 0.25
C25: 17 04 11 | D25: Cables distintos de los especificados en el código 17 04 10 | F25: Reciclado | H25: =IF(B25="X",J25*'EGR2 2--copiar en word 1 EGR'!D33,0) -> 0 | J25: 0.1
C26: 4. Papel
B27: x | C27: 20 01 01 | D27: Papel | F27: Reciclado | G27: Gestor autorizado RNPs | H27: ='EGR2 2--copiar en word 1 EGR'!D27 -> 0.35243955 | J27: Total tipo RCD
C28: 5. Plástico
B29: x | C29: 17 02 03 | D29: Plástico | F29: Reciclado | G29: Gestor autorizado RNPs | H29: ='EGR2 2--copiar en word 1 EGR'!D28 -> 1.7621978 | J29: Total tipo RCD
C30: 6. Vidrio
C31: 17 02 02 | D31: Vidrio | F31: Reciclado | G31: Gestor autorizado RNPs | H31: ='EGR2 2--copiar en word 1 EGR'!D29 -> 0.58739925 | J31: Total tipo RCD
C32: 7. Yeso
C33: 17 08 02 | D33: Materiales de construcción a partir de yeso distintos a los del código 17 08 01 | F33: Reciclado | G33: Gestor autorizado RNPs | H33: ='EGR2 2--copiar en word 1 EGR'!D30 -> 0.2349597 | J33: Total tipo RCD
C36: RCD: Naturaleza pétrea | F36: Tratamiento | G36: Destino | H36: Cantidad
C38: 1. Arena Grava y otros áridos
B39: x | C39: 01 04 08 | D39: Residuos de grava y rocas trituradas distintos de los mencionados en el código 01 04 07 | F39: Reciclado | G39: Planta de reciclaje RCD | H39: =IF(B39="X",J39*'EGR2 2--copiar en word 1 EGR'!D34,0) -> 1.1747985 | J39: 0.25
B40: x | C40: 01 04 09 | D40: Residuos de arena y arcilla | F40: Reciclado | G40: Planta de reciclaje RCD | H40: =IF(B40="X",'EGR2 2--copiar en word 1 EGR'!D34-H39,0) -> 3.5243955 | J40: Diferencia tipo RCD
C42: 2. Hormigón
B43: x | C43: 17 01 01 | D43: Hormigón | F43: Reciclado / Vertedero | G43: Planta de reciclaje RCD | H43: ='EGR2 2--copiar en word 1 EGR'!D35 -> 14.097582 | J43: Total tipo RCD
C45: 3. Ladrillos , azulejos y otros cerámicos
C46: 17 01 02 | D46: Ladrillos | F46: Reciclado | G46: Planta de reciclaje RCD | H46: =IF(B46="X",J46*'EGR2 2--copiar en word 1 EGR'!D36,0) -> 0 | J46: 0.35
C47: 17 01 03 | D47: Tejas y materiales cerámicos | F47: Reciclado | G47: Planta de reciclaje RCD | H47: =IF(B47="X",'EGR2 2--copiar en word 1 EGR'!D36-'EGR 3-copiar en word 2 EGR'!H46-'EGR 3-copiar en word 2 EGR'!H48,0) -> 0 | J47: Diferencia tipo RCD
C48: 17 01 07 | D48: Mezclas de hormigón, ladrillos, tejas y materiales cerámicos distintas de las especificadas en el código 1 7 01 06. | F48: Reciclado / Vertedero | G48: Planta de reciclaje RCD | H48: =IF(B48="X",J48*'EGR2 2--copiar en word 1 EGR'!D38,0) -> 0 | J48: 0.25
C50: 4. Piedra
B51: x | C51: 17 09 04 | D51: RDCs mezclados distintos a los de los códigos 17 09 01, 02 y 03 | F51: Reciclado | H51: ='EGR2 2--copiar en word 1 EGR'!D37 -> 5.8739925 | J51: Total tipo RCD
C54: RCD: Potencialmente peligrosos y otros | F54: Tratamiento | G54: Destino | H54: Cantidad
C56: 1. Basuras
B57: x | C57: 20 02 01 | D57: Residuos biodegradables | F57: Reciclado / Vertedero | G57: Planta de reciclaje RSU | H57: =IF(B57="X",J57*'EGR2 2--copiar en word 1 EGR'!D41,0) -> 2.8782563 | J57: 0.35
B58: x | C58: 20 03 01 | D58: Mezcla de residuos municipales | F58: Reciclado / Vertedero | G58: Planta de reciclaje RSU | H58: =IF(B58="X",'EGR2 2--copiar en word 1 EGR'!D41-'EGR 3-copiar en word 2 EGR'!H57,0) -> 5.3453332 | J58: Diferencia tipo RCD
C60: 2. Potencialmente peligrosos y otros
C61: 17 01 06 | D61: mezcal de hormigón, ladrillos, tejas y materilaes cerámicos con sustancias peligrosas (SP's) | F61: Depósito Seguridad | G61: Gestor autorizado RPs | H61: =IF(B61="X",J61*'EGR2 2--copiar en word 1 EGR'!$D$42,0) -> 0 | J61: 0.01
C62: 17 02 04 | D62: Madera, vidrio o plastico con sustancias peligrosas o contaminadas por ellas | F62: Tratamiento Fco-Qco | H62: =IF(B62="X",J62*'EGR2 2--copiar en word 1 EGR'!$D$42,0) -> 0 | J62: 0.01
C63: 17 03 01 | D63: Mezclas bituminosas que contienen alquitran de hulla | F63: Depósito / Tratamiento | H63: =IF(B63="X",J63*'EGR2 2--copiar en word 1 EGR'!$D$42,0) -> 0 | J63: 0.04
C64: 17 03 03 | D64: Alquitrán de hulla y productos alquitranados | F64: Depósito / Tratamiento | H64: =IF(B64="X",J64*'EGR2 2--copiar en word 1 EGR'!$D$42,0) -> 0 | J64: 0.015
C65: 17 04 09 | D65: Residuos metálicos contaminados con sustancias peligrosas | F65: Tratamiento Fco-Qco | H65: =IF(B65="X",J65*'EGR2 2--copiar en word 1 EGR'!$D$42,0) -> 0 | J65: 0.01
C66: 17 04 10 | D66: Cables que contienen hidrocarburos, alquitran de hulla y otras SP's | F66: Tratamiento Fco-Qco | H66: =IF(B66="X",J66*'EGR2 2--copiar en word 1 EGR'!$D$42,0) -> 0 | J66: 0.2
C67: 17 06 01 | D67: Materiales de aislamiento que contienen Amianto | F67: Depósito Seguridad | H67: =IF(B67="X",J67*'EGR2 2--copiar en word 1 EGR'!$D$42,0) -> 0 | J67: 0.01
C68: 17 06 03 | D68: Otros materiales de aislamiento que contienen sustancias peligrosas | F68: Depósito Seguridad | H68: =IF(B68="X",J68*'EGR2 2--copiar en word 1 EGR'!$D$42,0) -> 0 | J68: 0.01
C69: 17 06 05 | D69: Materiales de construcción que contienen Amianto | F69: Depósito Seguridad | H69: =IF(B69="X",J69*'EGR2 2--copiar en word 1 EGR'!$D$42,0) -> 0 | J69: 0.01
C70: 17 08 01 | D70: Materiales de construcción a partir de yeso contaminados con SP's | F70: Tratamiento Fco-Qco | H70: =IF(B70="X",J70*'EGR2 2--copiar en word 1 EGR'!$D$42,0) -> 0 | J70: 0.01
C71: 17 09 01 | D71: Residuos de construcción y demolición que contienen mercúrio | F71: Depósito Seguridad | H71: =IF(B71="X",J71*'EGR2 2--copiar en word 1 EGR'!$D$42,0) -> 0 | J71: 0.01
C72: 17 09 02 | D72: Residuos de construcción y demolición que contienen PCB's | F72: Depósito Seguridad | H72: =IF(B72="X",J72*'EGR2 2--copiar en word 1 EGR'!$D$42,0) -> 0 | J72: 0.01
C73: 17 09 03 | D73: Otros residuos de construcción y demolición que contienen SP's | F73: Depósito Seguridad | H73: =IF(B73="X",J73*'EGR2 2--copiar en word 1 EGR'!$D$42,0) -> 0 | J73: 0.01
C74: 17 06 04 | D74: Materiales de aislamientos distintos de los 17 06 01 y 03 | F74: Reciclado | G74: Gestor autorizado RNPs | H74: =IF(B74="X",J74*'EGR2 2--copiar en word 1 EGR'!$D$42,0) -> 0 | J74: 0.01
B75: x | C75: 17 05 03 | D75: Tierras y piedras que contienen SP's | F75: Tratamiento Fco-Qco | G75: Gestor autorizado RPs | H75: =IF(B75="X",J75*'EGR2 2--copiar en word 1 EGR'!$D$42,0) -> 0.04699194 | J75: 0.01
C76: 17 05 05 | D76: Lodos de drenaje que contienen sustancias peligrosas | F76: Tratamiento Fco-Qco | H76: =IF(B76="X",J76*'EGR2 2--copiar en word 1 EGR'!$D$42,0) -> 0 | J76: 0.01
C77: 17 05 07 | D77: Balastro de vías férreas que contienen sustancias peligrosas | F77: Depósito / Tratamiento | H77: =IF(B77="X",J77*'EGR2 2--copiar en word 1 EGR'!$D$42,0) -> 0 | J77: 0.01
B78: x | C78: 15 02 02 | D78: Absorventes contaminados (trapos,…) | F78: Depósito / Tratamiento | H78: =IF(B78="X",J78*'EGR2 2--copiar en word 1 EGR'!$D$42,0) -> 0.04699194 | J78: 0.01
C79: 13 02 05 | D79: Aceites usados (minerales no clorados de motor,…) | F79: Depósito / Tratamiento | H79: =IF(B79="X",J79*'EGR2 2--copiar en word 1 EGR'!$D$42,0) -> 0 | J79: 0.02
C80: 16 01 07 | D80: Filtros de aceite | F80: Depósito / Tratamiento | H80: =IF(B80="X",J80*'EGR2 2--copiar en word 1 EGR'!$D$42,0) -> 0 | J80: 0.01
C81: 20 01 21 | D81: Tubos fluorescentes | F81: Depósito / Tratamiento | H81: =IF(B81="X",J81*'EGR2 2--copiar en word 1 EGR'!$D$42,0) -> 0 | J81: 0.02
C82: 16 06 04 | D82: Pilas alcalinas y salinas | F82: Depósito / Tratamiento | H82: =IF(B82="X",J82*'EGR2 2--copiar en word 1 EGR'!$D$42,0) -> 0 | J82: 0.01
C83: 16 06 03 | D83: Pilas botón | F83: Depósito / Tratamiento | H83: =IF(B83="X",J83*'EGR2 2--copiar en word 1 EGR'!$D$42,0) -> 0 | J83: 0.01
B84: x | C84: 15 01 10 | D84: Envases vacíos de metal o plastico contaminado | F84: Depósito / Tratamiento | H84: =IF(B84="X",'EGR2 2--copiar en word 1 EGR'!D42-'EGR 3-copiar en word 2 EGR'!H93,0) -> 4.3702505 | J84: Diferencia tipo RCD
C85: 08 01 11 | D85: Sobrantes de pintura o barnices | F85: Depósito / Tratamiento | H85: =IF(B85="X",J85*'EGR2 2--copiar en word 1 EGR'!$D$42,0) -> 0 | J85: 0.2
C86: 14 06 03 | D86: Sobrantes de disolventes no halogenados | F86: Depósito / Tratamiento | H86: =IF(B86="X",J86*'EGR2 2--copiar en word 1 EGR'!$D$42,0) -> 0 | J86: 0.015
C87: 07 07 01 | D87: Sobrantes de desencofrantes | F87: Depósito / Tratamiento | H87: =IF(B87="X",J87*'EGR2 2--copiar en word 1 EGR'!$D$42,0) -> 0 | J87: 0.075
B88: x | C88: 15 01 11 | D88: Aerosoles vacios | F88: Depósito / Tratamiento | H88: =IF(B88="X",J88*'EGR2 2--copiar en word 1 EGR'!$D$42,0) -> 0.2349597 | J88: 0.05
C89: 16 06 01 | D89: Baterías de plomo | F89: Depósito / Tratamiento | H89: =IF(B89="X",J89*'EGR2 2--copiar en word 1 EGR'!$D$42,0) -> 0 | J89: 0.01
C90: 13 07 03 | D90: Hidrocarburos con agua | F90: Depósito / Tratamiento | H90: =IF(B90="X",J90*'EGR2 2--copiar en word 1 EGR'!$D$42,0) -> 0 | J90: 0.05
C91: 17 09 04 | D91: RDCs mezclados distintos códigos 17 09 01, 02 y 03 | F91: Depósito / Tratamiento | G91: Restauración / Vertedero | H91: =IF(B91="X",J91*'EGR2 2--copiar en word 1 EGR'!$D$42,0) -> 0 | J91: 0.02
H93: =SUM(H61:H83,H85:H91) -> 0.32894358

Sheet EGR 4-copiar en word 3 EGR
B2: A.- ESTIMACIÓN DEL COSTE DE TRATAMIENTO DE LOS RCDs
B4: Tipología RCDs | C4: Estimación (m³) | D4: Precio gestión en Planta / Vertedero / Cantera / Gestor (€/m³) | E4: Importe (€) | F4: Importe mínimo(€) | G4: % del presupuesto de Obra
B5: A1 RCDs Nivel I
B6: Tierras y pétreos de la excavación | C6: ='EGR2 2--copiar en word 1 EGR'!F18 -> 961.19878 | D6: 8 | E6: =C6*D6 -> 7689.5902 | F6: =MAX(E6,8) -> 7689.5902 | G6: =F6/'EGR2 2--copiar en word 1 EGR'!$C$11*100 -> 1.8148508
G7: =G6 -> 1.8148508
B9: A2 RCDs Nivel II
B10: RCDs Naturaleza Pétrea | C10: ='EGR2 2--copiar en word 1 EGR'!F38 -> 58.739925 | D10: 20 | E10: =C10*D10 -> 1174.7985 | F10: =MAX(E10,20) -> 1174.7985 | G10: =F10/'EGR2 2--copiar en word 1 EGR'!$C$11*100 -> 0.27726888
B11: RCDs Naturaleza No Pétrea (metales) | C11: ='EGR2 2--copiar en word 1 EGR'!F26 -> 1.9579975 | D11: 105 | E11: =C11*D11 -> 205.58974 | F11: =E11 -> 205.58974 | G11: =F11/'EGR2 2--copiar en word 1 EGR'!$C$11*100 -> 0.048522053
B12: RCDs Naturaleza No Pétrea (resto) | C12: ='EGR2 2--copiar en word 1 EGR'!F31-'EGR 4-copiar en word 3 EGR'!C11 -> 15.287442 | D12: 23 | E12: =C12*D12 -> 351.61117 | F12: =MAX(E12,23) -> 351.61117 | G12: =F12/'EGR2 2--copiar en word 1 EGR'!$C$11*100 -> 0.082985153
B13: RCDs Potencialmente peligrosos | C13: ='EGR2 2--copiar en word 1 EGR'!F43 -> 18.53571 | D13: 30 | E13: =C13*D13 -> 556.07129 | F13: =MAX(E13,30) -> 556.07129 | G13: =F13/'EGR2 2--copiar en word 1 EGR'!$C$11*100 -> 0.1312406
G14: =SUM(G10:G13) -> 0.54001668
B16: B.- RESTO DE COSTES DE GESTIÓN
B17: B1.- % Presupuesto hasta cubrir RCD Nivel I | E17: =G17/100*'EGR2 2--copiar en word 1 EGR'!$C$11 -> 0 | F17: =G17/100*'EGR2 2--copiar en word 1 EGR'!$C$11 -> 0 | G17: =IF(G7<0.2,0.2-G7,0) -> 0
B18: B2.- % Presupuesto hasta cubrir RCD Nivel II | E18: =G18/100*'EGR2 2--copiar en word 1 EGR'!$C$11 -> 0 | F18: =G18/100*'EGR2 2--copiar en word 1 EGR'!$C$11 -> 0 | G18: =IF(G14<0.2,0.2-G14,0) -> 0
B19: B3.- % Presupuesto de Obra por costes de gestión, alquileres, etc… | E19: =G19/100*'EGR2 2--copiar en word 1 EGR'!$C$11 -> 423.70371 | F19: =G19/100*'EGR2 2--copiar en word 1 EGR'!$C$11 -> 423.70371 | G19: 0.1
B21: TOTAL PRESUPUESTO PLAN GESTION RCDs | E21: =E6+E10+E11+E12+E13+E17+E18+E19 -> 10401.365 | F21: =F6+F10+F11+F12+F13+F17+F18+F19 -> 10401.365 | G21: =G7+G14+G17+G18+G19 -> 2.4548675
D30: =24/70 -> 0.34285714

Sheet ESS 1-input-copiar en word ESS
A1: PROCESO | B1: 1.- ENTRADA DATOS VERDES
B2: 2.- COPIAR EL PRESUPUESTO AL WORD
H5: Días totales | I5: Nº trabajadores (máximo) | J5: Duración estimada (meses) | K5: Fracción estimada anual | L5: Los días totales se estiman del archivo Excel de planificación. Se estiman 3 cuadrillas de 10 trabajadores
A6: Prevención y formación | H6: =+J6*20 -> 80 | I6: 10 | J6: 4 | K6: =+ROUNDUP(J6/12,2) -> 0.34
A8: Nº DE ORDEN | B8: DESCRIPCION | C8: HORAS - HOMBRE – MES | D8: PRECIO UNIDAD | E8: FRACCIÓN ESTIMADA | F8: COSTE (€)
A10: 1 | B10: Asistencia técnica, inspecciones, informes… | C10: 14 | D10: 57.33 | E10: =+J6 -> 4 | F10: =+C10*D10*E10 -> 3210.48
A11: 2 | B11: Reuniones de seguridad | C11: 0.5 | D11: 344.01 | E11: =+J6 -> 4 | F11: =+C11*D11*E11 -> 688.02
A12: 3 | B12: Formación | C12: 0.5 | D12: 573.35 | E12: =+J6 -> 4 | F12: =+C12*D12*E12 -> 1146.7
A13: Subtotal | F13: =SUM(F10:F12) -> 5045.2
A15: Servicio médico
A17: Nº DE ORDEN | B17: DESCRIPCION | C17: Nº DE OPERARIOS | D17: PRECIO UNIDAD | E17: FRACCIÓN ESTIMADA | F17: COSTE (€)
A19: 1 | B19: Reconocimiento médico | C19: =+I6 -> 10 | D19: 57.33 | E19: =+K6 -> 0.34 | F19: =+C19*D19*E19 -> 194.922
A20: Subtotal | F20: =+F19 -> 194.922
A22: Protecciones colectivas
A24: Nº DE ORDEN | B24: DESCRIPCION | C24: DOTACION ANUAL OPERARIO | D24: PRECIO UNIDAD (€) | E24: Nº DE OPERARIOS PREVISTOS | F24: FRACCIÓN ESTIMADA | G24: COSTE (€)
A26: 1 | B26: Cerramientos/vallas de obra | C26: 0.1 | D26: 7166.82 | E26: =I6 -> 10 | F26: =+K6/3 -> 0.11333333 | G26: =C26*D26*E26*F26 -> 812.2396
A27: 2 | B27: Barandillas | C27: 0.25 | D27: 86 | E27: =I6 -> 10 | F27: =+K6 -> 0.34 | G27: =+C27*D27*E27*F27 -> 73.1
A28: 3 | B28: Señalización zona de trabajo | C28: 0.25 | D28: 28.67 | E28: =I6 -> 10 | F28: =+K6 -> 0.34 | G28: =+C28*D28*E28*F28 -> 24.3695
A29: 4 | B29: Cintas de balizamiento | C29: 1 | D29: 21.5 | E29: =I6 -> 10 | F29: =+K6 -> 0.34 | G29: =+C29*D29*E29*F29 -> 73.1
A30: 5 | B30: Vallas metálicas | C30: 0.5 | D30: 57.33 | E30: =I6 -> 10 | F30: =+K6/3 -> 0.11333333 | G30: =+C30*D30*E30*F30 -> 32.487
A31: 6 | B31: Andamios | C31: 0.15 | D31: 2866.73 | E31: =I6 -> 10 | F31: =+K6 -> 0.34 | G31: =+C31*D31*E31*F31 -> 1462.0323
A32: 7 | B32: Chapa protección huecos | C32: 0.25 | D32: 95.56 | E32: =I6 -> 10 | F32: =+K6 -> 0.34 | G32: =+C32*D32*E32*F32 -> 81.226
A33: 8 | B33: Escaleras de mano | C33: 0.5 | D33: 114.67 | E33: =I6 -> 10 | F33: =+K6 -> 0.34 | G33: =+C33*D33*E33*F33 -> 194.939
A34: 9 | B34: Protección ferralla (setas plástico) | C34: 30 | D34: 0.36 | E34: =I6 -> 10 | F34: =+K6 -> 0.34 | G34: =+C34*D34*E34*F34 -> 36.72
A35: 10 | B35: Extintores portátiles | C35: 0.25 | D35: 32 | E35: =I6 -> 10 | F35: =+K6 -> 0.34 | G35: =+C35*D35*E35*F35 -> 27.2
A36: 11 | B36: Líneas de vida | C36: 0.5 | D36: 226.95 | E36: =I6 -> 10 | F36: =+K6 -> 0.34 | G36: =+C36*D36*E36*F36 -> 385.815
A37: Subtotal | G37: =SUM(G26:G36) -> 3203.2284
A39: Protecciones individuales
A41: Nº DE ORDEN | B41: DESCRIPCION | C41: DOTACION ANUAL OPERARIO | D41: PRECIO UNIDAD (€) | E41: Nº DE OPERARIOS PREVISTOS | F41: FRACCIÓN ESTIMADA | G41: COSTE (€)
A43: 1 | B43: Casco seguridad | C43: 1.25 | D43: 8.6 | E43: =+$I$6 -> 10 | F43: =+$K$6 -> 0.34 | G43: =C43*D43*E43*F43 -> 36.55
A44: 2 | B44: Gafas contra impactos | C44: 1 | D44: 43 | E44: =+$I$6 -> 10 | F44: =+$K$6 -> 0.34 | G44: =C44*D44*E44*F44 -> 146.2
A45: 3 | B45: Gafas ambientes pulvígenos | C45: 1 | D45: 43 | E45: =+$I$6 -> 10 | F45: =+$K$6 -> 0.34 | G45: =C45*D45*E45*F45 -> 146.2
A46: 4 | B46: Gafas soldadura autógena | C46: 1 | D46: 43 | E46: =+$I$6 -> 10 | F46: =+$K$6 -> 0.34 | G46: =C46*D46*E46*F46 -> 146.2
A47: 5 | B47: Guantes de trabajo | C47: 12 | D47: 7.17 | E47: =+$I$6 -> 10 | F47: =+$K$6 -> 0.34 | G47: =C47*D47*E47*F47 -> 292.536
A48: 6 | B48: Guantes de goma | C48: 3 | D48: 7.17 | E48: =+$I$6 -> 10 | F48: =+$K$6 -> 0.34 | G48: =C48*D48*E48*F48 -> 73.134
A49: 7 | B49: Guantes aislantes | C49: 1 | D49: 86.15 | E49: =+$I$6 -> 10 | F49: =+$K$6 -> 0.34 | G49: =C49*D49*E49*F49 -> 292.91
A50: 8 | B50: Pantalla arco eléctrico | C50: 1 | D50: 28.67 | E50: =+$I$6 -> 10 | F50: =+$K$6 -> 0.34 | G50: =C50*D50*E50*F50 -> 97.478
A51: 9 | B51: Mascarilla ambientes pulvígenos | C51: 6 | D51: 4.3 | E51: =+$I$6 -> 10 | F51: =+$K$6 -> 0.34 | G51: =C51*D51*E51*F51 -> 87.72
A52: 10 | B52: Protecciones auditivas | C52: 2 | D52: 17.2 | E52: =+$I$6 -> 10 | F52: =+$K$6 -> 0.34 | G52: =C52*D52*E52*F52 -> 116.96
A53: 11 | B53: Manguitos soldador | C53: 1 | D53: 31.06 | E53: =+$I$6 -> 10 | F53: =+$K$6 -> 0.34 | G53: =C53*D53*E53*F53 -> 105.604
A54: 12 | B54: Mandil soldador | C54: 1 | D54: 45.39 | E54: =+$I$6 -> 10 | F54: =+$K$6 -> 0.34 | G54: =C54*D54*E54*F54 -> 154.326
... A62: 20 | B62: Chaleco reflectante | C62: 0.5 | D62: 50.17 | E62: =+$I$6 -> 10 | F62: =+$K$6 -> 0.34 | G62: =C62*D62*E62*F62 -> 85.289
A63: Subtotal | G63: =SUM(G43:G62) -> 3048.763
A65: Instalaciones de Higiene y Primeros Auxilios
A67: Nº DE ORDEN | B67: DESCRIPCION | C67: PRECIO UNIDAD (€) | D67: FRACCIÓN ESTIMADA | E67: COSTE (€)
A69: 1 | B69: Mes alquiler caseta prefabricada oficina | C69: 860.02 | D69: =J6 -> 4 | E69: =C69*D69 -> 3440.08
A70: 2 | B70: Mes alquiler caseta prefabricada aseos y vestuarios | C70: 860.02 | D70: =J6 -> 4 | E70: =C70*D70 -> 3440.08
A71: 3 | B71: Botiquín sanitario de obra | C71: 215 | D71: ---- | E71: 215
A72: Subtotal | E72: =SUM(E69:E71) -> 7095.16
A76: Concepto | B76: Importe
A77: Prevención y formación | B77: =+F13 -> 5045.2
A78: Servicio médico | B78: =+F20 -> 194.922
A79: Protecciones colectivas | B79: =+G37 -> 3203.2284
A80: Protecciones individuales | B80: =+G63 -> 3048.763
A81: Instalaciones de Higiene y Primeros Auxilios | B81: =+E72 -> 7095.16
A82: TOTAL PRESUPUESTO DE SEGURIDAD Y SALUD- | B82: =SUM(B77:B81) -> 18587.273
